Workbook

Sheet Guidelines
A1: Tab Name | B1: Description | C1: Starting number of papers | D1: Final number of papers | E1: Inclusion Criteria Applied | H1: Exculsion Criteria applied
A2: Overall Dataset | B2: Set of paper retrieved from the digital libraries. It represents the dataset used for primary screening. | C2: 5147 | D2: =COUNTA('Overall Dataset'!E:E)-1 -> 3146 | E2: ID | F2: Description | G2: RQ | H2: ID | I2: Description
E3: IC1 | F3: Paper is published between 2015 and 2025 | H3: EC1 | I3: Paper is a graduate thesis or project report
E4: IC2 | F4: Paper is either a Conference or Journal paper | H4: EC2 | I4: Paper has not been peer-reviewed
E5: IC3 | F5: Paper is not a duplicate across multiple sources
A6: Preliminary Screening | B6: Checking the title and abstract of each included paper over 5 rounds considering the keywords as per EC3. Round 1: Manually done by Eoan Round 2 - 5: Automated in python A paper is included if at least one round opted to include the paper | C6: =D2 -> 3146 | D6: 215 | E6: IC4 | F6: Paper is written in English based on title and abstract | H6: EC3 | I6: Paper does not mention (cloud application or micro) and (energy or sustainability or green) in the title or abstract
A7: Primary Screening | B7: Reading the title and abstract of each included paper over three rounds. Round 1: Manually done by Eoan Round 2: Done by a LLM (GPT-4o-mini) Round 3: Done by a LLM (GTP-4o-mini) A paper is included if at least one round opted to include the paper | C7: 215 | D7: 117 | E7: IC5 | F7: Title/abstract indicates energy efficiency/consumption is considered in software engineering or architecture. | H7: EC4 | I7: Only discusses energy at hardware/infrastructure level, not software/architecture.
E8: IC6 | F8: Title/abstract refers to solutions for energy-efficient microservices. | H8: EC5 | I8: No mention of measurement, analysis, or evaluation of energy in microservices.
H9: EC6 | I9: The paper is a secondary study (SLR, mapping studies...)
A10: Secondary Screening | B10: Reading the introduction and conclusion of each included paper | C10: =D7 -> 117 | D10: =SUMIF('Secondary Screening Dataset'!A:A, "1") -> 55 | E10: IC7 | F10: The introduction/conclusion talks about how to engineer green MS | G10: RQ1 | H10: EC4 | I10: The introduction/conclusion only discusses energy at hardware/infrastructure level, not software/architecture.
E11: IC8 | F11: The introduction/conclusion discusses how they measure energy consumption in MS | G11: RQ2 | H11: EC5 | I11: The introduction/conclusion does not mention measurement, analysis, or evaluation of energy in microservices.
E12: IC9 | F12: Introduction/conclusion refers to solutions for energy-efficient microservices. | G12: RQ3 | H12: EC7 | I12: The full text of the paper is not accessible
A13: Final Screening | B13: Reading the full text of each paper | C13: =D10 -> 55 | D13: 37 | E13: P1 | F13: The text indicates that EE is considered across one or more software lifecycle stages in MS based systems. | G13: RQ1.1
E14: P2 | F14: The text refers to EC related to specific MS architectural elements (e.g. services, containers, gateways). | G14: RQ1.2
E15: P3 | F15: The text indicates methods to measure or assess EC in MS systems. | G15: RQ2.1
E16: P4 | F16: The text mentions the use or development of specific tools for analyzing or monitoring energy in MS. | G16: RQ2.2
E17: P5 | F17: The text refers to the use or development of metrics for evaluating energy efficiency in MS systems. | G17: RQ2.3
E18: P6 | F18: The text presents or summarizes architectural approaches or solutions aimed at improving EE in MS. | G18: RQ3.1
E19: P7 | F19: The text mentions trade-offs between EE and other system qualities (e.g., performance, scalability). | G19: RQ3.2
E20: P8 | F20: The text discusses challenges or barriers to implementing EE in MS. | G20: RQ3.3
A21: Final Set of Papers | C21: 37
A22: List of Parameters | B22: The tab reports the list of parameters with description. In addition, the list of possible values for parameters are listed and described. | D22: None | F22: None

Sheet Snowball Process
A1: Step # | B1: Tab Name | C1: Description | D1: Starting number of papers | E1: Final number of papers | F1: Inclusion Criteria Applied | I1: Exculsion Criteria applied | M1: Snowball Repeats
A2: 1 | B2: Overall Dataset | C2: Set of paper retrieved from the digital libraries. It represents the dataset used for primary screening. | D2: Forward: 1001 Backward: 1503 Total: 2504 | E2: 403 | F2: ID | G2: Description | H2: RQ | I2: ID | J2: Description | M2: Checks to make (Snowball)
F3: IC1 | G3: Paper is published between 2015 and 2025 | I3: EC1 | J3: Paper is a graduate thesis or project report | M3: - Check against first dataset (3146) - Only English - Peer reviewed - Remove duplicates - Between 2015 - 2025
F4: IC2 | G4: Paper is either a Conference or Journal paper | I4: EC2 | J4: Paper has not been peer-reviewed
F5: IC3 | G5: Paper is not a duplicate across multiple sources | I5: EC3 | J5: The paper was in the original dataset
B6: Preliminary Screening | C6: Checking the title and abstract of each included paper over 2 rounds considering the keywords as per EC3. Round 1 - 2: Automated in python A paper is included if at least one round opted to include the paper | D6: =E2 -> 403 | E6: 25 | F6: IC4 | G6: Paper is written in English based on title and abstract | I6: EC3 | J6: Paper does not mention (cloud application or micro) and (energy or sustainability or green) in the title or abstract | M6: Asreview settings - Do one randomly - Do one 80/20
B7: Primary Screening | C7: Reading the title and abstract of each included paper over three rounds. Round 1: Manually done by Eoan Round 2: Done by a LLM (GPT-4o-mini) Round 3: Done by a LLM (GTP-4o-mini) A paper is included if at least one round opted to include the paper | D7: =E6 -> 25 | E7: 12 | F7: IC5 | G7: Title/abstract indicates energy efficiency/consumption is considered in software engineering or architecture. | I7: EC4 | J7: Only discusses energy at hardware/infrastructure level, not software/architecture.
F8: IC6 | G8: Title/abstract refers to solutions for energy-efficient microservices. | I8: EC5 | J8: No mention of measurement, analysis, or evaluation of energy in microservices.
I9: EC6 | J9: The paper is a secondary study (SLR, mapping studies...)
B10: Secondary Screening | C10: Reading the introduction and conclusion of each included paper | D10: 12 | E10: 9 | F10: IC7 | G10: The introduction/conclusion talks about how to engineer green MS | H10: RQ1 | I10: EC7 | J10: The introduction/conclusion only discusses energy at hardware/infrastructure level, not software/architecture. | M10: Read introduction/conclusion
F11: IC8 | G11: The introduction/conclusion discusses how they measure energy consumption in MS | H11: RQ2 | I11: EC8 | J11: The introduction/conclusion does not mention measurement, analysis, or evaluation of energy in microservices.
F12: IC9 | G12: Introduction/conclusion refers to solutions for energy-efficient microservices. | H12: RQ3 | I12: EC9 | J12: The full text of the paper is not accessible
B13: Final Screening | D13: 9 | E13: 3 | F13: P1 | G13: The text indicates that EE is considered across one or more software lifecycle stages in MS based systems. | H13: RQ1.1
F14: P2 | G14: The text refers to EC related to specific MS architectural elements (e.g. services, containers, gateways). | H14: RQ1.2
F15: P3 | G15: The text indicates methods to measure or assess EC in MS systems. | H15: RQ2.1
F16: P4 | G16: The text mentions the use or development of specific tools for analyzing or monitoring energy in MS. | H16: RQ2.2
F17: P5 | G17: The text refers to the use or development of metrics for evaluating energy efficiency in MS systems. | H17: RQ2.3
F18: P6 | G18: The text presents or summarizes architectural approaches or solutions aimed at improving EE in MS. | H18: RQ3.1
F19: P7 | G19: The text mentions trade-offs between EE and other system qualities (e.g., performance, scalability). | H19: RQ3.2
F20: P8 | G20: The text discusses challenges or barriers to implementing EE in MS. | H20: RQ3.3
B21: Final Set of Papers
B22: List of Parameters | C22: The tab reports the list of parameters with description. In addition, the list of possible values for parameters are listed and described. | E22: None | G22: None

Sheet Parameters
A1: PARAMETER ID | B1: Parameter Name | C1: Type | D1: Example Values | E1: Description
A2: RQ1: Where is energy efficiency considered in microservice architecture research?
A3: RQ1.1: At which stages of the software lifecycle is energy efficiency considered in microservices?
A4: RQ1.1.P1 | B4: Energy Consideration Stage | C4: Single | D4: Requirements, Design, Implementation, Testing, Deployment, Operations | E4: At what point in the lifecycle energy efficiency becomes a stated concern or point of attention | H4: =IFERROR(__xludf.DUMMYFUNCTION("CONCAT(A4,CONCAT(""_"", REGEXREPLACE(B4, "" "", """")))"),"RQ1.1.P1_EnergyConsiderationStage") -> RQ1.1.P1_EnergyConsiderationStage
A5: RQ1.1.P2 | B5: Energy Intervention Stage | C5: Single | D5: Explicit requirements, Implicit concerns, Post-deployment optimization | E5: At what point in the lifecycle energy efficiency concerns are addressed | H5: =IFERROR(__xludf.DUMMYFUNCTION("CONCAT(A5,CONCAT(""_"", REGEXREPLACE(B5, "" "", """")))"),"RQ1.1.P2_EnergyInterventionStage") -> RQ1.1.P2_EnergyInterventionStage
A6: RQ1.1.P3 | B6: Energy Optimisation Technique | C6: Single | D6: Build-in, Add-on, External monitoring, Manual assessment | E6: How energy efficiency is introduced into the system or process | H6: =IFERROR(__xludf.DUMMYFUNCTION("CONCAT(A6,CONCAT(""_"", REGEXREPLACE(B6, "" "", """")))"),"RQ1.1.P3_EnergyOptimisationTechnique") -> RQ1.1.P3_EnergyOptimisationTechnique
A7: RQ1.2: Which microservice architectural elements are primarily considered when measuring energy consumption?
A8: RQ1.2.P1 | B8: Component Type | C8: Single | D8: Service units, API Gateways, Message brokers, Databases, Load balancers, Containers | E8: Captures the architectural element to which energy consumption is measured or attributed. | H8: =IFERROR(__xludf.DUMMYFUNCTION("CONCAT(A8,CONCAT(""_"", REGEXREPLACE(B8, "" "", """")))"),"RQ1.2.P1_ComponentType") -> RQ1.2.P1_ComponentType
A9: RQ1.2.P2 | B9: Energy consumption source | C9: Multiple | D9: Processing overhead, Communication overhead, State management, Resource allocation, Idle consumption | E9: The type of system activity responsible for the measured energy consumption. | H9: =IFERROR(__xludf.DUMMYFUNCTION("CONCAT(A9,CONCAT(""_"", REGEXREPLACE(B9, "" "", """")))"),"RQ1.2.P2_Energyconsumptionsource") -> RQ1.2.P2_Energyconsumptionsource
A10: RQ1.2.P3 | B10: Component Relationship | C10: Single | D10: Isolated, Interconnected, Cascading effect, System-wide impact | E10: Describes how interactions and dependencies between components are characterised when reasoning about energy efficiency | H10: =IFERROR(__xludf.DUMMYFUNCTION("CONCAT(A10,CONCAT(""_"", REGEXREPLACE(B10, "" "", """")))"),"RQ1.2.P3_ComponentRelationship") -> RQ1.2.P3_ComponentRelationship
A11: RQ2: How is energy consumption measured in microservices?
A12: RQ2.1: What methods are used to measure energy consumption in microservices?
A13: RQ2.1.P1 | B13: Measurement Level | C13: Single | D13: Hardware, OS, Container, Application, Cross-cutting | E13: Represents at which level energy consumption is measured | H13: =IFERROR(__xludf.DUMMYFUNCTION("CONCAT(A13,CONCAT(""_"", REGEXREPLACE(B13, "" "", """")))"),"RQ2.1.P1_MeasurementLevel") -> RQ2.1.P1_MeasurementLevel
A14: RQ2.1.P2 | B14: Measurement Technique | C14: Single | D14: Static analysis, Dynamic profiling, Model-based estimation, Hybrid | E14: Describes the technique used to measure energy consumption | H14: =IFERROR(__xludf.DUMMYFUNCTION("CONCAT(A14,CONCAT(""_"", REGEXREPLACE(B14, "" "", """")))"),"RQ2.1.P2_MeasurementTechnique") -> RQ2.1.P2_MeasurementTechnique
A15: RQ2.1.P3 | B15: Data Collection | C15: Single | D15: Sampling, Continuous monitoring, Event-triggered, Benchmark testing | E15: Refers to the method of collecting energy consumption data | H15: =IFERROR(__xludf.DUMMYFUNCTION("CONCAT(A15,CONCAT(""_"", REGEXREPLACE(B15, "" "", """")))"),"RQ2.1.P3_DataCollection") -> RQ2.1.P3_DataCollection
A16: RQ2.1.P4 | B16: Implementation Approach | C16: Single | D16: Source code instrumentation, Binary instrumentation, External monitoring | E16: Indicates the approach used to implement the measurement | H16: =IFERROR(__xludf.DUMMYFUNCTION("CONCAT(A16,CONCAT(""_"", REGEXREPLACE(B16, "" "", """")))"),"RQ2.1.P4_ImplementationApproach") -> RQ2.1.P4_ImplementationApproach
A17: RQ2.2: How are tools used for energy consumption analysis in microservices?
A18: RQ2.2.P1 | B18: Tool Type | C18: Single | D18: Commercial, Open source, Research prototype, Custom in-house | E18: Categorizes the type of tools used for energy consumption analysis | H18: =IFERROR(__xludf.DUMMYFUNCTION("CONCAT(A18,CONCAT(""_"", REGEXREPLACE(B18, "" "", """")))"),"RQ2.2.P1_ToolType") -> RQ2.2.P1_ToolType
A19: RQ2.2.P2 | B19: Deployment Method | C19: Single | D19: Agent-based, Sidecar, External, Embedded | E19: Describes how the tool is deployed within the system | H19: =IFERROR(__xludf.DUMMYFUNCTION("CONCAT(A19,CONCAT(""_"", REGEXREPLACE(B19, "" "", """")))"),"RQ2.2.P2_DeploymentMethod") -> RQ2.2.P2_DeploymentMethod
A20: RQ2.2.P3 | B20: Analysis Capability | C20: Single | D20: Real-time, Historical, Predictive, Comparative | E20: Defines the type of analysis the tool provides | H20: =IFERROR(__xludf.DUMMYFUNCTION("CONCAT(A20,CONCAT(""_"", REGEXREPLACE(B20, "" "", """")))"),"RQ2.2.P3_AnalysisCapability") -> RQ2.2.P3_AnalysisCapability
A21: RQ2.2.P4 | B21: Granularity | C21: Single | D21: System-wide, Service-specific, Transaction-level, Code-block level | E21: Indicates the level of detail at which the tool analyzes energy consumption | H21: =IFERROR(__xludf.DUMMYFUNCTION("CONCAT(A21,CONCAT(""_"", REGEXREPLACE(B21, "" "", """")))"),"RQ2.2.P4_Granularity") -> RQ2.2.P4_Granularity
A22: RQ2.3: What energy efficiency metrics are commonly used to evaluate microservices?
A23: RQ2.3.P1 | B23: Metric Type | C23: Single | D23: Absolute (Joules, Watts), Relative (efficiency ratio), Composite | E23: The type of metric used to evaluate energy efficiency | H23: =IFERROR(__xludf.DUMMYFUNCTION("CONCAT(A23,CONCAT(""_"", REGEXREPLACE(B23, "" "", """")))"),"RQ2.3.P1_MetricType") -> RQ2.3.P1_MetricType
A24: RQ2.3.P2 | B24: Measurement Scope | C24: Multiple | D24: CPU, Memory, Network, Storage, Full-stack | E24: The speicif system resource or scope being measureed for energy consumption | H24: =IFERROR(__xludf.DUMMYFUNCTION("CONCAT(A24,CONCAT(""_"", REGEXREPLACE(B24, "" "", """")))"),"RQ2.3.P2_MeasurementScope") -> RQ2.3.P2_MeasurementScope
A25: RQ2.3.P3 | B25: Normalization Basis | C25: Multiple | D25: Per request, Per transaction, Per user, Per service | E25: Defines how energy consumption is normalized to provide meaningful comparisons | H25: =IFERROR(__xludf.DUMMYFUNCTION("CONCAT(A25,CONCAT(""_"", REGEXREPLACE(B25, "" "", """")))"),"RQ2.3.P3_NormalizationBasis") -> RQ2.3.P3_NormalizationBasis
A26: RQ2.3.P4 | B26: Business Relevance | C26: Multiple | D26: Cost-focused, Performance-balanced, Carbon footprint | E26: Represents the business-oriented perspective of the metric | H26: =IFERROR(__xludf.DUMMYFUNCTION("CONCAT(A26,CONCAT(""_"", REGEXREPLACE(B26, "" "", """")))"),"RQ2.3.P4_BusinessRelevance") -> RQ2.3.P4_BusinessRelevance
A27: RQ3: What architectural solutions exist for energy-efficient microservices?
A28: RQ3.1: What approaches are used to improve energy efficiency in microservice architectures?
A29: RQ3.1.P1 | B29: Energy Management Strategy | C29: Single | D29: Strangler pattern, Incremental refactoring, Complete rebuild, Containerization | E29: How existing systems are updated for energy efficiency | H29: =IFERROR(__xludf.DUMMYFUNCTION("CONCAT(A29,CONCAT(""_"", REGEXREPLACE(B29, "" "", """")))"),"RQ3.1.P1_EnergyManagementStrategy") -> RQ3.1.P1_EnergyManagementStrategy
A30: RQ3.1.P2 | B30: Tactic Category | C30: Single | D30: Architectural patterns, Design patterns, Resource management tactics, Request handling tactics, Data management tactics | E30: Types of patterns and tactics used to improve energy efficiency | H30: =IFERROR(__xludf.DUMMYFUNCTION("CONCAT(A30,CONCAT(""_"", REGEXREPLACE(B30, "" "", """")))"),"RQ3.1.P2_TacticCategory") -> RQ3.1.P2_TacticCategory
A31: RQ3.1.P3 | B31: Implementation Technologies | C31: Single | D31: Containerization, Serverless, Service mesh, Orchestration platforms, Green computing frameworks | E31: Specific technologies enabling energy-efficient solutions | H31: =IFERROR(__xludf.DUMMYFUNCTION("CONCAT(A31,CONCAT(""_"", REGEXREPLACE(B31, "" "", """")))"),"RQ3.1.P3_ImplementationTechnologies") -> RQ3.1.P3_ImplementationTechnologies
A32: RQ3.2: What trade-offs exist between energy efficiency and other quality attributes in microservice architectures?
A33: RQ3.2.P1 | B33: Quality Attribute | C33: Multiple | D33: Performance, Scalability, Maintainability, Reliability, Security, Availability | E33: System qualities impacted by energy efficiency efforts | H33: =IFERROR(__xludf.DUMMYFUNCTION("CONCAT(A33,CONCAT(""_"", REGEXREPLACE(B33, "" "", """")))"),"RQ3.2.P1_QualityAttribute") -> RQ3.2.P1_QualityAttribute
A34: RQ3.2.P2 | B34: Trade-off Relationship | C34: Single | D34: Competing, Complementary, Context-dependent, Independent | E34: Nature of the interaction between energy efficiency and other qualities | H34: =IFERROR(__xludf.DUMMYFUNCTION("CONCAT(A34,CONCAT(""_"", REGEXREPLACE(B34, "" "", """")))"),"RQ3.2.P2_Trade-offRelationship") -> RQ3.2.P2_Trade-offRelationship
A35: RQ3.2.P3 | B35: Trade-off Strategy | C35: Single | D35: Architectural refactoring, Compensating tactics, Prioritization frameworks, Incremental evolution | E35: Methods to manage or mitigate trade-offs | H35: =IFERROR(__xludf.DUMMYFUNCTION("CONCAT(A35,CONCAT(""_"", REGEXREPLACE(B35, "" "", """")))"),"RQ3.2.P3_Trade-offStrategy") -> RQ3.2.P3_Trade-offStrategy
A36: RQ3.3: What challenges affect the adoption of energy-efficient architectural solutions in microservices?
A37: RQ3.3.P1 | B37: Challenge Type | C37: Single | D37: Technical, Organizational, Knowledge-based, Economic | E37: Type of challenges to adoptation | H37: =IFERROR(__xludf.DUMMYFUNCTION("CONCAT(A37,CONCAT(""_"", REGEXREPLACE(B37, "" "", """")))"),"RQ3.3.P1_ChallengeType") -> RQ3.3.P1_ChallengeType
A38: RQ3.3.P2 | B38: Adoption Phase | C38: Single | D38: Design-time, Implementation, Deployment, Runtime | E38: Lifecycle phase where challenges occur | H38: =IFERROR(__xludf.DUMMYFUNCTION("CONCAT(A38,CONCAT(""_"", REGEXREPLACE(B38, "" "", """")))"),"RQ3.3.P2_AdoptionPhase") -> RQ3.3.P2_AdoptionPhase
A39: RQ3.3.P3 | B39: Challenge Complexity | C39: Single | E39: Difficulty level of the challenge | H39: =IFERROR(__xludf.DUMMYFUNCTION("CONCAT(A39,CONCAT(""_"", REGEXREPLACE(B39, "" "", """")))"),"RQ3.3.P3_ChallengeComplexity") -> RQ3.3.P3_ChallengeComplexity
A40: RQ3.3.P4 | B40: Mitigation Approach | C40: Single | D40: Tooling improvements, Knowledge sharing, Incremental adoption, Organizational change | E40: Strategies to address challenges | H40: =IFERROR(__xludf.DUMMYFUNCTION("CONCAT(A40,CONCAT(""_"", REGEXREPLACE(B40, "" "", """")))"),"RQ3.3.P4_MitigationApproach") -> RQ3.3.P4_MitigationApproach

Sheet Search Strings
A1: Iteration | B1: Search String | C1: Type | D1: Results
A2: 5 | B2: ("microservice" OR "micro-service" OR "microservices" OR "micro-services") AND ("energy consumption" OR "power consumption" OR "energy efficiency") AND ("measurement" OR "measurements" OR "profiling" OR "monitoring") AND ("tradeoff" OR "trade-off" OR "quality" OR "qualities") AND ("pattern" OR "patterns" OR "tactic" OR "tactics") | C2: General
B3: ("microservice" OR "micro-service" OR "microservices" OR "micro-services") AND ("energy consumption" OR "power consumption" OR "energy efficiency") AND ("measurement" OR "measurements" OR "profiling" OR "monitoring") AND ("tradeoff" OR "trade-off" OR "quality" OR "qualities") AND ("pattern" OR "patterns" OR "tactic" OR "tactics") AND PUBYEAR > 2014 AND PUBYEAR < 2026 | C3: Scopus
B4: (("Full Text Only":"microservice*") OR ("Full Text Only":"micro-service*")) AND (("Full Text Only":"energy consumption") OR ("Full Text Only":"power consumption") OR ("Full Text Only":"energy efficiency")) AND (("Full Text Only":"measurement*") OR ("Full Text Only":"profiling") OR ("Full Text Only":"monitoring")) AND (("Full Text Only":"trade*off*") OR ("Full Text Only":"qualit*")) AND (("Full Text Only":"pattern*") OR ("Full Text Only":"tactic*")) | C4: IEEE
D5: Database | E5: Total Results | F5: Conference + Journal Papers
D6: ACM | E6: 564 | F6: 554
D7: ACM Expanded | E7: 1052 | F7: 589
D8: IEEE | E8: 1285 | F8: 1041
D9: Scopus | E9: 307 | F9: 215
D10: Springer | E10: 622 | F10: 407
A12: 6 (Selected) | B12: ("microservice" OR "micro-service" OR "microservices" OR "micro-services") AND ("energy consumption" OR "power consumption" OR "energy efficiency") AND ("measurement" OR "measurements" OR "profiling" OR "monitoring") AND ("tradeoff" OR "trade-off" OR "quality" OR "qualities" OR "pattern" OR "patterns" OR "tactic" OR "tactics") | C12: General
B13: ("microservice" OR "micro-service" OR "microservices" OR "micro-services") AND ("energy consumption" OR "power consumption" OR "energy efficiency") AND ("measurement" OR "measurements" OR "profiling" OR "monitoring") AND ("tradeoff" OR "trade-off" OR "quality" OR "qualities" OR "pattern" OR "patterns" OR "tactic" OR "tactics") AND PUBYEAR > 2014 AND PUBYEAR < 2026 | C13: Scopus
B14: (("Full Text Only":"microservice*") OR ("Full Text Only":"micro-service*")) AND (("Full Text Only":"energy consumption") OR ("Full Text Only":"power consumption") OR ("Full Text Only":"energy efficiency")) AND (("Full Text Only":"measurement*") OR ("Full Text Only":"profiling") OR ("Full Text Only":"monitoring")) AND (("Full Text Only":"trade*off*") OR ("Full Text Only":"qualit*") OR ("Full Text Only":"pattern*") OR ("Full Text Only":"tactic*")) | C14: IEEE
D15: Database | E15: Total Results | F15: Conference + Journal Papers
D16: ACM | E16: 739 | F16: 720 | G16: 720
D17: ACM Expanded | E17: 1495 | F17: 806 (658 | G17: 806
D18: IEEE | E18: 2459 | F18: 2107 (1414 conference) | G18: 2107
D19: Scopus | E19: 1031 | F19: 804 | G19: 804
D20: Springer | E20: 1020 | F20: 710 | G20: 710

Sheet ASReview Results Overview
A1: Round # | B1: Date | C1: # Relevant | D1: # Labeled | E1: Notes
A2: Round 1 | B2: 45748 | C2: 142 | D2: 1664 | E2: Maximum
A3: Round 2 | B3: 45798 | C3: 156 | D3: 2291 | E3: 5% randomness
A4: Round 3 | B4: 45798 | C4: 199 | D4: 3146 | E4: 5% randomness
A5: Round 4 | B5: 45798 | C5: 190 | D5: 2102 | E5: 0 randomness
A6: Round 5 | B6: 45798 | C6: 193 | D6: 2292 | E6: 0 randomness
A9: Round # | B9: Date | C9: # Relevant | D9: # Labeled | E9: Notes
A10: Round 1 | B10: 45957 | C10: 25 | D10: 403 | E10: Maximum
A11: Round 2 | B11: 45957 | C11: 25 | D11: 403 | E11: 5% randomness

Sheet Overall Dataset
A1: Key | B1: Item Type | C1: Publication Year | D1: Author | E1: Title | F1: Publication Title | G1: ISBN | H1: ISSN | I1: DOI | J1: Url | K1: Date | L1: Date Added | M1: Date Modified | N1: Access Date | O1: Pages | P1: Num Pages | Q1: Issue | R1: Volume | S1: Number Of Volumes | T1: Journal Abbreviation | U1: Short Title | V1: Series | W1: Series Number | X1: Series Text | Y1: Series Title | Z1: Publisher | AA1: Place | AB1: Language | AC1: Rights | AD1: Type | AE1: Archive | AF1: Archive Location | AG1: Library Catalog | AH1: Call Number | AI1: Extra | AJ1: Notes | AK1: File Attachments | AL1: Link Attachments | AM1: Automatic Tags | AN1: Editor | AO1: Series Editor | AP1: Translator | AQ1: Contributor | AR1: Attorney Agent | AS1: Book Author | AT1: Cast Member | AU1: Commenter | AV1: Composer | AW1: Cosponsor | AX1: Counsel | AY1: Interviewer | AZ1: Producer | BA1: Recipient | BB1: Reviewed Author | BC1: Scriptwriter | BD1: Words By | BE1: Guest | BF1: Number | BG1: Edition | BH1: Running Time | BI1: Scale | BJ1: Medium | BK1: Artwork Size | BL1: Filing Date | BM1: Application Number | BN1: Assignee | BO1: Issuing Authority | BP1: Country | BQ1: Meeting Name | BR1: Conference Name | BS1: Court | BT1: References | BU1: Reporter | BV1: Legal Status | BW1: Priority Numbers | BX1: Programming Language | BY1: Version | BZ1: System | CA1: Code | CB1: Code Number | CC1: Section | CD1: Session | CE1: Committee | CF1: History | CG1: Legislative Body | CH1: Author Affiliations | CI1: Date Added To Xplore | CJ1: Start Page | CK1: End Page | CL1: Abstract | CM1: ISBNs | CN1: Funding Information | CO1: PDF Link | CP1: Author Keywords | CQ1: Mesh_Terms | CR1: Article Citation Count | CS1: Patent Citation Count | CT1: Reference Count | CU1: License | CV1: Issue Date | CW1: Meeting Date | CX1: Author full names | CY1: Author(s) ID | CZ1: Year | DA1: Source title | DB1: Art. No. | DC1: Page start | DD1: Page end | DE1: Page count | DF1: Cited by | DG1: Link | DH1: Publication Stage | DI1: Open Access | DJ1: Source | DK1: EID | DL1: Keywords
A2: PPQI2ZES | B2: conferencePaper | C2: 2024 | D2: Serrano-Gutierrez, Pablo; Ayala, Inmaculada | E2: Using Energy Consumption for Self-adaptation in&nbsp;FaaS | F2: Reuse and Software Quality: 21st International Conference on Software and Systems Reuse, ICSR 2024, Limassol, Cyprus, June 19‚Äì20, 2024, Proceedings | G2: 978-3-031-66458-8 | I2: 10.1007/978-3-031-66459-5_8 | J2: https://doi.org/10.1007/978-3-031-66459-5_8 | K2: 2024 | L2: 45734.379 | M2: 45734.379 | O2: 123‚Äì134 | Z2: Springer-Verlag | AA2: Berlin, Heidelberg | AI2: event-place: Limassol, Cyprus | CL2: One of the programming models that has been developing the most in recent years is Function as a Service (FaaS). The growing concern over data centre energy footprints has driven sustainable software development. In serverless applications, energy consumption depends on the energy consumption of the application‚Äôs functions. However, measuring energy proves challenging, and the results‚Äô variability complicates optimisation efforts at runtime. This article addresses this issue by measuring serverless function energy consumption and exploring integration into an optimisation system that selects implementations based on their current energy footprint. For this, we have integrated an energy measurement software into a FaaS system. We have analysed how to properly process the data and how to use them to perform self-adaptation. We present a series of methods and policies that make our system not only capable of detecting variations in the energy consumption of the functions, but it does so taking into account the variability in the measurements that each function may present. Our experiments showcase proper integration in a self-adaptive system, showing a reduction up to 5% in energy consumption due to functions in a test application. | DL2: serverless; sustainability; self-adaptive
A3: MF6HYN8W | B3: conferencePaper | C3: 2024 | D3: Galantino, Stefano; Pinto, Andrea; Esposito, Flavio; Manzalini, Antonio; Risso, Fulvio | E3: Balancing Energy Efficiency and Infrastructure Knowledge in Cloud-to-Edge Task Distribution Systems | F3: Proceedings of the 1st International Workshop on MetaOS for the Cloud-Edge-IoT Continuum | G3: 979-8-4007-0543-4 | I3: 10.1145/3642975.3678965 | J3: https://doi.org/10.1145/3642975.3678965 | K3: 2024 | L3: 45734.379 | M3: 45734.379 | O3: 28‚Äì34 | V3: MECC '24 | Z3: Association for Computing Machinery | AA3: New York, NY, USA | AI3: event-place: Athens, Greece | CL3: In the rapidly evolving landscape of distributed computing, maintaining energy efficiency in edge and data center infrastructures has become critical. While the problem has been faced with centralized approaches assuming knowledge of the available underlying infrastructure resources, this paper introduces a distributed task allocation framework emphasizing energy awareness without requiring infrastructure knowledge. The framework is designed to optimize energy consumption in heterogeneous computing environments, leveraging a distributed consensus algorithm that allows nodes to maximize individual or global goals. Each private custom utility function enables a node to carefully determine whether executing a task is efficient, thus ensuring flexibility in the task allocation process based on local preferences. While showcasing the energy efficiency of our framework, we also illustrate that it is not necessary to disclose the underlying infrastructure resources status, ensuring the preservation of potentially sensitive local resources information. Experimental results demonstrate the framework's ability to achieve optimal power consumption outcomes while maintaining privacy, offering a significant advancement over traditional centralized allocation policies and Kubernetes-like scheduling algorithms.
A4: LKFV3LAA | B4: conferencePaper | C4: 2022 | D4: M√ºller, Benedikt Tobias; Ender, Marvin; Swiadek, Jan Erik; Jin, Mengcheng; Winkel, Simon; Niedziela, Dominik; Li, Bin; H√ºntelmann, Jelle; M√ºller, Emmanuel | E4: ADEPT: Anomaly Detection, Explanation and Processing for Time Series with a Focus on Energy Consumption Data | F4: Machine Learning and Knowledge Discovery in Databases: European Conference, ECML PKDD 2022, Grenoble, France, September 19‚Äì23, 2022, Proceedings, Part VI | G4: 978-3-031-26421-4 | I4: 10.1007/978-3-031-26422-1_43 | J4: https://doi.org/10.1007/978-3-031-26422-1_43 | K4: 2022 | L4: 45734.379 | M4: 45734.379 | O4: 622‚Äì626 | Z4: Springer-Verlag | AA4: Berlin, Heidelberg | AI4: event-place: Grenoble, France | CL4: Anomaly detection techniques are applicable for recognizing excessive energy consumption and device failure, thereby contributing to the maintenance of operational and sustainable energy supply systems. In this context, human decision makers can benefit from receiving explanation attempts for detected anomalies as part of a semi-automated software solution. Therefore we introduce the framework ADEPT, which comprises interfaces for processing user-supplied time series data and interactively visualizing explanatory anomaly information. Our framework features several shallow and deep machine learning algorithms for anomaly detection and explanation. We demonstrate ADEPT using energy consumption data collected from our university campus. | DL4: Anomaly detection; Energy consumption; Explainability
A5: ZIKASWQT | B5: conferencePaper | C5: 2023 | D5: Sim√µes, Bruno; Del Puy Carretero, Mar√≠a; Martinez Santiago, Jorge; Mu√±oz Segovia, Sebastian; Alcain, Nieves | E5: TwinArk: A Unified Framework for Digital Twins based on Micro-frontends, Micro-Services, and Web 3D | F5: Proceedings of the 28th International ACM Conference on 3D Web Technology | G5: 979-8-4007-0324-9 | I5: 10.1145/3611314.3615915 | J5: https://doi.org/10.1145/3611314.3615915 | K5: 2023 | L5: 45734.379 | M5: 45734.379 | V5: Web3D '23 | Z5: Association for Computing Machinery | AA5: New York, NY, USA | AI5: event-place: San Sebastian, Spain | CL5: The introduction of the Digital Twin (DT) has sparked a great deal of interest in the virtual replication of physical assets and processes. However, to fully realize the potential of DT, companies require robust and scalable front-end solutions. This study proposes harnessing micro-frontend technologies to surmount the limitations of monolithic front-end frameworks, thereby crafting effective presentation layers tailored for industrial companies. By decomposing complex and distributed systems into modular web-based DT, the proposed framework enables better scalability, synergy, and efficient application development. It also tackles the intricacies introduced by complex multi-vendor elements within DT and the orchestration of services and virtual environments. Research is focused on developing an architecture that facilitates seamless connectivity between multiple blocks of DT as well as interactivity and immersive experiences. Our study offers insights into our journey of implementing this framework for various industrial use cases, such as training, monitoring, and control, highlighting the benefits, drawbacks, and challenges. Ultimately, this research aims to accelerate the creation of DT, improve maintainability, and increase efficiency and productivity in industrial environments. | DL5: digital twins; GUI; Web3D
A6: 87Y8HT3V | B6: conferencePaper | C6: 2019 | D6: Duarte, Lucio Mauro; da Silva Alves, Danilo; Toresan, Bruno Ramos; Maia, Paulo Henrique; Silva, Davi | E6: A Model-based Framework for the Analysis of Software Energy Consumption | F6: Proceedings of the XXXIII Brazilian Symposium on Software Engineering | G6: 978-1-4503-7651-8 | I6: 10.1145/3350768.3353813 | J6: https://doi.org/10.1145/3350768.3353813 | K6: 2019 | L6: 45734.379 | M6: 45734.379 | O6: 67‚Äì72 | V6: SBES '19 | Z6: Association for Computing Machinery | AA6: New York, NY, USA | AI6: event-place: Salvador, Brazil | CL6: Software is present in all types of devices, some of them with restrictions as to the amount of energy they can spend to execute software applications. For this reason, energy costs are becoming an important factor during software development and evolution. However, there is still little support for creating energy-efficient software. In this work, we introduce a possible framework for software energy costs evaluation based on model analysis. We model software as Labelled Transitions Systems (LTS) and annotate these models with energy costs, which can be obtained using existing tools. We can then apply graph-based algorithms to traverse the models to obtain information about energy consumption related to software behaviour, such as its most/least costly execution, the cost of a specific execution, and the average cost of executing the software. No existing tool currently provides all the necessary analyses, even though they are essential for energy-consumption evaluation. We have conducted a small experiment with our framework where we employed jRAPL to measure energy costs. We annotated the models with the collected energy costs using an extended version of the LoTuS tool, where we have also implemented some of the desired analyses. Based on this support and on our initial results, we believe developers could create software more energy-efficient and consider possible trade-offs related to time, space, and energy costs when producing new versions of their systems. | DL6: Embedded Software; Energy Consumption Evaluation; Labelled Transition System; Model-based Analysis
A7: HPFCIEF2 | B7: conferencePaper | C7: 2019 | D7: Lin, Pingrong; Lin, Zheyuan; Shi, Xiaoquan | E7: Research on Optimization of Course Selection System Based on Micro service and Dynamic Resource Extension | F7: Proceedings of the 4th International Conference on Big Data and Computing | G7: 978-1-4503-6278-8 | I7: 10.1145/3335484.3335546 | J7: https://doi.org/10.1145/3335484.3335546 | K7: 2019 | L7: 45734.379 | M7: 45734.379 | O7: 115‚Äì119 | V7: ICBDC '19 | Z7: Association for Computing Machinery | AA7: New York, NY, USA | AI7: event-place: Guangzhou, China | CL7: In view of the fact that the course selection system in Colleges and universities has short burst access, large concurrent business and complex business, and combined with the existing course selection system of South China Institute of Software Engineering of Guangzhou University, an optimization scheme based on micro service and dynamic resource extension is constructed. The scheme can solve the problem of low performance of course selection system by building a micro-service architecture, splitting the business services of course selection system, scaling up the cluster of servers, and expanding the resources dynamically. The performance comparison before and after optimization shows that the performance of the course selection system has been greatly improved, and the scheme is feasible and effective. | DL7: micro-service; course selection system; dynamic resource expansion
A8: 8YLDVF6H | B8: conferencePaper | C8: 2022 | D8: Tang, Wenda; Ke, Yutao; Fu, Senbo; Jiang, Hongliang; Wu, Junjie; Peng, Qian; Gao, Feng | E8: Demeter: QoS-aware CPU scheduling to reduce power consumption of multiple black-box workloads | F8: Proceedings of the 13th Symposium on Cloud Computing | G8: 978-1-4503-9414-7 | I8: 10.1145/3542929.3563476 | J8: https://doi.org/10.1145/3542929.3563476 | K8: 2022 | L8: 45734.379 | M8: 45734.379 | O8: 31‚Äì46 | V8: SoCC '22 | Z8: Association for Computing Machinery | AA8: New York, NY, USA | AI8: event-place: San Francisco, California | CL8: Energy consumption in cloud data centers has become an increasingly important contributor to greenhouse gas emissions and operation costs. To reduce energy-related costs and improve environmental sustainability, most modern data centers consolidate Virtual Machine (VM) workloads belonging to different application classes, some being latency-critical (LC) and others being more tolerant to performance changes, known as best-effort (BE). However, in public cloud scenarios, the real classes of applications are often opaque to data center operators. The heterogeneous applications from different cloud tenants are usually consolidated onto the same hosts to improve energy efficiency, but it is not trivial to guarantee decent performance isolation among colocated workloads. We tackle the above challenges by introducing Demeter, a QoS-aware power management controller for heterogeneous black-box workloads in public clouds. Demeter is designed to work without offline profiling or prior knowledge about black-box workloads. Through the correlation analysis between network throughput and CPU resource utilization, Demeter automatically classifies black-box workloads as either LC or BE. By provisioning differentiated CPU management strategies (including dynamic core allocation and frequency scaling) to LC and BE workloads, Demeter achieves considerable power savings together with a minimum impact on the performance of all workloads. We discuss the design and implementation of Demeter in this work, and conduct extensive experimental evaluations to reveal its effectiveness. Our results show that Demeter not only meets the performance demand of all workloads, but also responds quickly to dynamic load changes in our cloud environment. In addition, Demeter saves an average of 10.6% power consumption than state of the art mechanisms. | DL8: cloud computing; power management; quality of service; workload characterization
A9: XXKXIWC6 | B9: conferencePaper | C9: 2021 | D9: Valera, Hernan Humberto Alvarez; Dalmau, Marc; Roose, Philippe; Larracoechea, Jorge; Herzog, Christina | E9: An energy saving approach: understanding microservices as multidimensional entities in p2p networks | F9: Proceedings of the 36th Annual ACM Symposium on Applied Computing | G9: 978-1-4503-8104-8 | I9: 10.1145/3412841.3441888 | J9: https://doi.org/10.1145/3412841.3441888 | K9: 2021 | L9: 45734.379 | M9: 45734.379 | O9: 69‚Äì78 | V9: SAC '21 | Z9: Association for Computing Machinery | AA9: New York, NY, USA | AI9: event-place: Virtual Event, Republic of Korea | CL9: With the use of microservices, many software solutions have been improved in terms of scalability, response efficiency, ease of load balancing among others. However, it is still a challenge to dynamically deploy them according to devices' heterogeneity and energy consumption concerns, while maintaining a defined QoS. Centralized and decentralized approaches that manage microservices deployment have the traditional pros and cons long discussed over time. While the former offer greater control over distributed application components, the latter offers frugal network negotiations, no system-wide crashes, privacy, among others.This work focuses on identifying "ideal" host candidates for microservices' execution in a decentralized network, applying run-time scheduling operations (migration or duplication) to reduce energy consumption. To do this, we created a scheduling algorithm using MAAN (a P2P approach) to interpret a decentralized network as a multidimensional resource (capacity-demand) space, which supports range queries in a logarithmic quantity of hops. In this way, a node that runs a set of microservices is able to 1) map them in terms of their execution requirements (i.e. CPU frequency, RAM capacity, Network rate and disk speed) 2) Select an ideal microservice to be moved or duplicated, 3) find ideal node(s) that meet all those requirements in an optimal computational complexity and 4) negotiate the movement or duplication of the selected microservice, by analyzing energy consumption and QoS criteria. | DL9: cloud computing; microservices; power consumption; energy consumption; distributed algorithms; P2P
A10: 9PLCWDL9 | B10: conferencePaper | C10: 2023 | D10: Nam, T. B.; Khiem, H. G.; Triet, M. N.; Hong, K. V.; Khoa, T. D.; Bao, Q. T.; Phuc, N. T.; Hieu, M. D.; Loc, V. C. P.; Quy, T. L.; Anh, N. T.; Hien, Q. N.; Bang, L. K.; Trong, D. P. N.; Ngan, N. T. K.; Son, H.; Luong, H. H. | E10: SPaMeR: Securing Patient Medical Records in&nbsp;the&nbsp;Cloud - A Microservice and&nbsp;Brokerless Architecture Approach | F10: Web Services ‚Äì ICWS 2023: 30th International Conference, Held as Part of the Services Conference Federation, SCF 2023, Honolulu, HI, USA, September 23‚Äì26, 2023, Proceedings | G10: 978-3-031-44835-5 | I10: 10.1007/978-3-031-44836-2_3 | J10: https://doi.org/10.1007/978-3-031-44836-2_3 | K10: 2023 | L10: 45734.379 | M10: 45734.379 | O10: 32‚Äì46 | Z10: Springer-Verlag | AA10: Berlin, Heidelberg | AI10: event-place: Honolulu, HI, USA | CL10: The expansion of Internet of Things (IoT) technologies has revolutionized various sectors, one of the most critical being healthcare. The effective management of Patient Medical Records (PMRs) is an area where IoT plays a significant role, and its integration with Cloud Computing offers an enormous opportunity to enhance data accessibility, efficiency, and cost-effectiveness. However, the challenge of securing PMRs in the cloud remains a key concern. This paper introduces SPaMeR, an innovative IoT platform based on microservice and brokerless architecture, tailored to address this challenge and the specific requirements of healthcare environments. SPaMeR platform incorporates and extends the core functionalities of the IoT platform designed in our previous work - data collection, device and user management, and remote device control - while specifically addressing six critical issues for healthcare data: a) secure and reliable transmission of medical data, b) energy efficiency for healthcare devices, c) high-speed and accurate data collection from medical devices, d) robust security mechanisms to protect sensitive patient information, e) scalability to accommodate the ever-growing number of patients and medical devices, and f) compliance with healthcare data regulations and standards. To demonstrate the effectiveness and feasibility of SPaMeR, we provide a comprehensive evaluation with two distinct healthcare scenarios. Our results indicate significant improvements in the areas of data security, energy efficiency, and system scalability compared to traditional healthcare platforms. | DL10: microservice; micro-service; Internet of Things; Kafka; brokerless; gRPC; Medical record; RBAC; Single Sign-On
A11: VG2IIX98 | B11: conferencePaper | C11: 2024 | D11: D'Angelo, Andrea; d'Aloisio, Giordano | E11: Grammar-Based Anomaly Detection of Microservice Systems Execution Traces | F11: Companion of the 15th ACM/SPEC International Conference on Performance Engineering | G11: 979-8-4007-0445-1 | I11: 10.1145/3629527.3651844 | J11: https://doi.org/10.1145/3629527.3651844 | K11: 2024 | L11: 45734.379 | M11: 45734.379 | O11: 77‚Äì81 | V11: ICPE '24 Companion | Z11: Association for Computing Machinery | AA11: New York, NY, USA | AI11: event-place: London, United Kingdom | CL11: Microservice architectures are a widely adopted architectural pattern for large-scale applications. Given the large adoption of these systems, several works have been proposed to detect performance anomalies starting from analysing the execution traces. However, most of the proposed approaches rely on machine learning (ML) algorithms to detect anomalies. While ML methods may be effective in detecting anomalies, the training and deployment of these systems as been shown to be less efficient in terms of time, computational resources, and energy required.In this paper, we propose a novel approach based on Context-free grammar for anomaly detection of microservice systems execution traces. We employ the SAX encoding to transform execution traces into strings. Then, we select strings encoding anomalies, and for each possible anomaly, we build a Context-free grammar using the Sequitur grammar induction algorithm. We test our approach on two real-world datasets and compare it with a Logistic Regression classifier. We show how our approach is more effective in terms of training time of 15 seconds with a minimum loss in effectiveness of 5% compared to the Logistic Regression baseline. | DL11: anomaly detection; context-free grammar; execution traces; micro service system
A12: BL8MQIZ4 | B12: conferencePaper | C12: 2023 | D12: Attarha, Shadi; Forster, Anna | E12: Empowering IoT Applications with Flexible, Energy-Efficient Remote Management of Low-Power Edge Devices | F12: Proceedings of the 2023 International Conference on Embedded Wireless Systems and Networks | K12: 2023 | L12: 45734.379 | M12: 45734.379 | O12: 52‚Äì55 | V12: EWSN '23 | Z12: Association for Computing Machinery | AA12: New York, NY, USA | AI12: event-place: Rende, Italy | CL12: In the context of the Internet of Things (IoT), reliable and energy-efficient provision of IoT applications has become critical. Equipping IoT systems with tools that enable a flexible, well-performing, and automated way of monitoring and managing IoT edge devices is an essential prerequisite. In current IoT systems, low-power edge appliances have been utilized in a way that can not be controlled and re-configured in a timely manner. Hence, conducting a trade-off solution between manageability, performance and design requirements are demanded. This paper introduces a novel approach for fine-grained monitoring and managing individual micro-services within low-power edge devices, which improves system reliability and energy efficiency. The proposed method enables operational flexibility for IoT edge devices by leveraging a modularization technique. Following a review of existing solutions for remote-managed IoT services, a detailed description of the suggested approach is presented. Also, to explore the essential design principles that must be considered in this approach, the suggested architecture is elaborated in detail. Finally, the advantages of the proposed solution to deal with disruptions are demonstrated in the proof of concept-based experiments. | DL12: IoT; Energy Efficiency; Low-power; Operational Flexibility; Service Isolation; Service Management
A13: PCR376C8 | B13: conferencePaper | C13: 2024 | D13: Steidl, Monika; Leitner, Michael; Urbanke, Pirmin; Gattringer, Marko; Felderer, Michael; Ristov, Sashko | E13: Understanding Microservice Runtime Monitoring Data for&nbsp;Anomaly Detection with&nbsp;Structural Equation Modeling | F13: Product-Focused Software Process Improvement: 25th International Conference, PROFES 2024, Tartu, Estonia, December 2‚Äì4, 2024, Proceedings | G13: 978-3-031-78385-2 | I13: 10.1007/978-3-031-78386-9_31 | J13: https://doi.org/10.1007/978-3-031-78386-9_31 | K13: 2024 | L13: 45734.379 | M13: 45734.379 | O13: 404‚Äì413 | Z13: Springer-Verlag | AA13: Berlin, Heidelberg | AI13: event-place: Tartu, Estonia | CL13: Microservices reliability is critical, but runtime anomalies are increasingly common due to system complexity. Rule-based and AI-based anomaly detection methods assist practitioners in analyzing runtime monitoring data (logs, traces, metrics) to identify anomalies. However, these methods rely&nbsp;on high-quality datasets and deep domain knowledge to deliver accurate results. Thus, a significant challenge lies in the lack of consensus on which runtime monitoring parameters effectively represent&nbsp;the system and microservices, reliably indicate anomalies,&nbsp;or distinguish deviations that genuinely signal anomalies. A thorough understanding of the dataset, key monitoring parameters,&nbsp;and microservice dependencies is crucial to minimize bias and&nbsp;false positives, ultimately improving the effectiveness of anomaly detection methods.Thus, we investigate whether structural equation modeling&nbsp;can describe the system‚Äôs or microservices‚Äô behavior via indicators extracted from runtime monitoring data and identify their causal relationships. We used EvoMaster to simulate user behavior&nbsp;in TrainTicket and extract runtime monitoring data to test our model. Our results show that the identified indicators effectively describe microservices‚Äô behavior, but network indicators alone&nbsp;are insufficient for describing the whole system‚Äôs behavior. The&nbsp;model can also identify microservices that significantly influence&nbsp;the whole system‚Äôs behavior. | DL13: Metrics; Anomaly detection during runtime; Logs; Microservice; Monitoring data; PLS-SEM; Structural equation model; Traces
A14: 2PZIJ4MJ | B14: conferencePaper | C14: 2024 | D14: Mehran, Narges; Kimovski, Dragi; Hellwagner, Hermann; Roman, Dumitru; Soylu, Ahmet; Prodan, Radu | E14: Scheduling of Distributed Applications on the Computing Continuum: A Survey | F14: Proceedings of the IEEE/ACM 16th International Conference on Utility and Cloud Computing | G14: 979-8-4007-0234-1 | I14: 10.1145/3603166.3632540 | J14: https://doi.org/10.1145/3603166.3632540 | K14: 2024 | L14: 45734.379 | M14: 45734.379 | V14: UCC '23 | Z14: Association for Computing Machinery | AA14: New York, NY, USA | AI14: event-place: Taormina (Messina), Italy | CL14: The demand for distributed applications has significantly increased over the past decade, with improvements in machine learning techniques fueling this growth. These applications predominantly utilize Cloud data centers for high-performance computing and Fog and Edge devices for low-latency communication for small-size machine learning model training and inference. The challenge of executing applications with different requirements on heterogeneous devices requires effective methods for solving NP-hard resource allocation and application scheduling problems. The state-of-the-art techniques primarily investigate conflicting objectives, such as the completion time, energy consumption, and economic cost of application execution on the Cloud, Fog, and Edge computing infrastructure. Therefore, in this work, we review these research works considering their objectives, methods, and evaluation tools. Based on the review, we provide a discussion on the scheduling methods in the Computing Continuum. | DL14: energy efficiency; cloud; computing continuum; edge; placement; scheduling
A15: UVN6593I | B15: conferencePaper | C15: 2024 | D15: Vahabi, Shahrokh; Righetti, Francesca; Vallati, Carlo; Tonellotto, Nicola | E15: Energy-Efficient Resource Management for Real-Time Applications in FaaS Edge Computing Platforms | F15: Proceedings of the IEEE/ACM 16th International Conference on Utility and Cloud Computing | G15: 979-8-4007-0234-1 | I15: 10.1145/3603166.3632240 | J15: https://doi.org/10.1145/3603166.3632240 | K15: 2024 | L15: 45734.379 | M15: 45734.379 | V15: UCC '23 | Z15: Association for Computing Machinery | AA15: New York, NY, USA | AI15: event-place: Taormina (Messina), Italy | CL15: Edge computing and Function-as-a-Service are two emerging paradigms that enable a timed analysis of data directly in the proximity of cyber-physical systems and users. Function-as-a-service platforms deployed at the edge require mechanisms for resource management and allocation to schedule function execution and to scale the available resources in order to ensure the proper quality of service to applications. Large-scale deployments will also require mechanisms to control the energy consumption of the overall system, to ensure long-term sustainability. In this paper, we propose a technique to schedule function invocations on Edge resources by powering down idle edge nodes during period of low demands. In doing so, our technique aims at reducing the overall energy consumption without incurring in service level agreements violations. Experimental evaluations demonstrate that the proposed approach reduces service level agreement violations by at least 78.1% and energy consumption by at least 62.5% on average using synthetic and real-world datasets w.r.t. different baselines. | DL15: energy efficiency; resource management; edge computing; function-as-a-service; service level agreement
A16: 8IY924WC | B16: conferencePaper | C16: 2023 | D16: Dinga, Madalina; Malavolta, Ivano; Giamattei, Luca; Guerriero, Antonio; Pietrantuono, Roberto | E16: An Empirical Evaluation of&nbsp;the&nbsp;Energy and&nbsp;Performance Overhead of&nbsp;Monitoring Tools on&nbsp;Docker-Based Systems | F16: Service-Oriented Computing: 21st International Conference, ICSOC 2023, Rome, Italy, November 28 ‚Äì December 1, 2023, Proceedings, Part I | G16: 978-3-031-48420-9 | I16: 10.1007/978-3-031-48421-6_13 | J16: https://doi.org/10.1007/978-3-031-48421-6_13 | K16: 2023 | L16: 45734.379 | M16: 45734.379 | O16: 181‚Äì196 | Z16: Springer-Verlag | AA16: Berlin, Heidelberg | AI16: event-place: Rome, Italy | CL16: Context. Energy efficiency is gaining importance in the design of software systems, but is still marginally addressed in the area of microservice-based systems. Energy-related aspects often get neglected in favor of other software quality attributes, such as performance, service composition, maintainability, and security.Goal. The aim of this study is to identify, synthesize and empirically evaluate the energy and performance overhead of monitoring tools employed in the microservices and DevOps context.Method. We selected four representative monitoring tools in the microservices and DevOps context. These were evaluated via a controlled experiment on an open-source Docker-based microservice benchmark system.Results. The results highlight: i) the specific frequency and workload conditions under which energy consumption and performance metrics are impacted by the tools; ii) the differences between the tools; iii) the relation between energy and performance overhead.
A17: 64HBXE4Z | B17: conferencePaper | C17: 2023 | D17: Khairy, Mahmoud; Alawneh, Ahmad; Barnes, Aaron; Rogers, Timothy G. | E17: SIMR: Single Instruction Multiple Request Processing for Energy-Efficient Data Center Microservices | F17: Proceedings of the 55th Annual IEEE/ACM International Symposium on Microarchitecture | G17: 978-1-6654-6272-3 | I17: 10.1109/MICRO56248.2022.00040 | J17: https://doi.org/10.1109/MICRO56248.2022.00040 | K17: 2023 | L17: 45734.379 | M17: 45734.379 | O17: 441‚Äì463 | V17: MICRO '22 | Z17: IEEE Press | AA17: Chicago, Illinois, USA | CL17: Contemporary data center servers process thousands of similar, independent requests per minute. In the interest of programmer productivity and ease of scaling, workloads in data centers have shifted from single monolithic processes toward a micro and nanoservice software architecture. As a result, single servers are now packed with many threads executing the same, relatively small task on different data.State-of-the-art data centers run these microservices on multi-core CPUs. However, the flexibility offered by traditional CPUs comes at an energy-efficiency cost. The Multiple Instruction Multiple Data execution model misses opportunities to aggregate the similarity in contemporary microservices. We observe that the Single Instruction Multiple Thread execution model, employed by GPUs, provides better thread scaling and has the potential to reduce frontend and memory system energy consumption. However, contemporary GPUs are ill-suited for the latency-sensitive microservice space.To exploit the similarity in contemporary microservices, while maintaining acceptable latency, we propose the Request Processing Unit (RPU). The RPU combines elements of out-of-order CPUs with lockstep thread aggregation mechanisms found in GPUs to execute microservices in a Single Instruction Multiple Request (SIMR) fashion. To complement the RPU, we also propose a SIMR-aware software stack that uses novel mechanisms to batch requests based on their predicted control-flow, split batches based on predicted latency divergence and map per-request memory allocations to maximize coalescing opportunities. Our resulting RPU system processes 5.7√ó more requests/joule than multi-core CPUs, while increasing single thread latency by only 1.44√ó. | DL17: data center; GPU; microservices; SIMT
A18: 3QBSZ9JC | B18: conferencePaper | C18: 2023 | D18: Thiede, John; Bashir, Noman; Irwin, David; Shenoy, Prashant | E18: Carbon Containers: A System-level Facility for Managing Application-level Carbon Emissions | F18: Proceedings of the 2023 ACM Symposium on Cloud Computing | G18: 979-8-4007-0387-4 | I18: 10.1145/3620678.3624644 | J18: https://doi.org/10.1145/3620678.3624644 | K18: 2023 | L18: 45734.379 | M18: 45734.379 | O18: 17‚Äì31 | V18: SoCC '23 | Z18: Association for Computing Machinery | AA18: New York, NY, USA | AI18: event-place: Santa Cruz, CA, USA | CL18: To reduce their environmental impact, cloud datacenters' are increasingly focused on optimizing applications' carbon-efficiency, or work done per mass of carbon emitted. To facilitate such optimizations, we present Carbon Containers, a simple system-level facility, which extends prior work on power containers, that automatically regulates applications' carbon emissions in response to variations in both their work-load's intensity and their energy's carbon-intensity. Specifically, Carbon Containers enable applications to specify a maximum carbon emissions rate (in g.CO2e/hr), and then transparently enforce this rate via a combination of vertical scaling, container migration, and suspend/resume while maximizing either energy-efficiency or performance.Carbon Containers are especially useful for applications that i) must continue running even during high-carbon periods, and ii) execute in regions with few variations in carbon-intensity. These low-variability regions also tend to have high average carbon-intensity, which increases the importance of regulating carbon emissions. We implement a Carbon Container prototype by extending Linux Containers to incorporate the mechanisms above and evaluate it using real workload traces and carbon-intensity data from multiple regions. We compare Carbon Containers with prior work that regulates carbon emissions by suspending/resuming applications during high/low carbon periods. We show that Carbon Containers are more carbon-efficient and improve performance while maintaining similar carbon emissions. | DL18: Carbon-efficiency; energy-efficiency; performance
A19: 96TRIUD2 | B19: conferencePaper | C19: 2024 | D19: Kawalkar, Shreyash N | E19: Geo-Intelligent Architecture for Smart Grid Evolution: Addressing Contemporary Challenges through Spatial AI and Knowledge Integration | F19: Proceedings of the 2023 4th Asia Service Sciences and Software Engineering Conference | G19: 979-8-4007-0853-4 | I19: 10.1145/3634814.3634838 | J19: https://doi.org/10.1145/3634814.3634838 | K19: 2024 | L19: 45734.379 | M19: 45734.379 | O19: 171‚Äì180 | V19: ASSE '23 | Z19: Association for Computing Machinery | AA19: New York, NY, USA | AI19: event-place: Aizu-Wakamatsu City, Japan | CL19: This research explores the challenges of contemporary Smart Grid (SG) technology products and proposes a novel methodology to address them. Through a comprehensive survey, we identified common hurdles SG technologies face, especially with the rapid evolution of technology and the expansion of energy sector assets. Central to our methodology is the development of a conceptual architecture that is adaptive, scalable, and optimized for complex data management. Key features of this architecture include a Modular Architecture with Micro-Services, Serverless 2.0 for Scalability, and the integration of Knowledge Graphs for enhanced data-driven decision-making. At the heart of these solutions lies the synthesis of geospatial intelligence via Geo-Spatial AI and the use of cognitive mapping to bridge micro-services with energy assets, to ensure the grid's responsive adjustment to dynamic energy landscapes. By synthesizing advanced AI technologies and geospatial mapping techniques, our approach promises a leap in efficiency, adaptability, and accuracy for future Smart Grid platforms. | DL19: AI in Modern Energy Infrastructures; AI Solutions for Smart Grid Technology Challenges; Cognitive Mapping of Micro Services to Energy Assets; Context aware Energy Management System; Geo Intelligent Software Architecture; Knowledge Graph Embedded AI; Streamlined Smart Grid Assets and Data Management
A20: H8PR9FFY | B20: conferencePaper | C20: 2021 | D20: Lamprakos, Christos P.; Marantos, Charalampos; Papadopoulos, Lazaros; Soudris, Dimitrios | E20: The Known Unknowns: Discovering Trade-Offs Between Heterogeneous Code Changes: Invited Paper | F20: Embedded Computer Systems: Architectures, Modeling, and Simulation: 21st International Conference, SAMOS 2021, Virtual Event, July 4‚Äì8, 2021, Proceedings | G20: 978-3-031-04579-0 | I20: 10.1007/978-3-031-04580-6_23 | J20: https://doi.org/10.1007/978-3-031-04580-6_23 | K20: 2021 | L20: 45734.379 | M20: 45734.379 | O20: 342‚Äì353 | Z20: Springer-Verlag | AA20: Berlin, Heidelberg | AI20: event-place: Samos, Greece | CL20: Software projects must adhere to a variety of non-functional requirements, also known as software qualities. Automated evaluation with respect to such requirements can be conducted thanks to a wide array of available tools. Each tool usually focuses on a specific quality, since heterogeneous analyses are needed for each non-functional requirement. Apart from an overall index expressing the project‚Äôs performance in terms of the software quality they specialize on, many tools recommend code changes that are expected to improve the aforementioned index. Thus, a development team that cares for more than one non-functional requirement is facing the problem of unknown trade-offs; besides improving the quality on which the tool that generated each suggestion focuses, how would this code change, if implemented, affect the rest of the non-functional requirements? We present a framework for dealing with this problem. We pick energy efficiency, technical debt and software security as our qualities of interest, and use three respective tools for the analysis of several open-source projects with regard to these qualities. We develop an extensible empirical model, based on fuzzy sets, for the characterization of each suggestion‚Äôs trade-offs. Finally, we present an intuitive visualization of said trade-offs, and suggest a method of utilizing them towards reliable decision-making. | DL20: Software quality; Trade-off analysis; Decision-making
A21: J9KHST7N | B21: conferencePaper | C21: 2024 | D21: Ghosh, Anyesha; Yadwadkar, Neeraja J.; Erez, Mattan | E21: Fast and Efficient Scaling for Microservices with SurgeGuard | F21: Proceedings of the International Conference for High Performance Computing, Networking, Storage, and Analysis | G21: 979-8-3503-5291-7 | I21: 10.1109/SC41406.2024.00103 | J21: https://doi.org/10.1109/SC41406.2024.00103 | K21: 2024 | L21: 45734.379 | M21: 45734.379 | V21: SC '24 | Z21: IEEE Press | AA21: Atlanta, GA, USA | CL21: The microservice architecture is increasingly popular for flexible, large-scale online applications. However, existing resource management mechanisms incur high latency in detecting Quality of Service (QoS) violations, and hence, fail to allocate resources effectively under commonly-observed varying load conditions. This results in over-allocation coupled with a late response that increase both the total cost of ownership and the magnitude of each QoS violation event. We present SurgeGuard, a decentralized resource controller for microservice applications specifically designed to guard application QoS during surges in load and network latency. SurgeGuard uses the key insight that for rapid detection and effective management of QoS violations, the controller must be aware of any available slack in latency and communication patterns between microservices within a task-graph. Our experiments show that for the workloads in DeathStarBench, SurgeGuard on average reduces the combined violation magnitude and duration by 61.1%% and 93.7%%, respectively, compared to the well-known Parties and Caladan algorithms, and requires 8% fewer resources than Parties. | DL21: Cloud computing; microservices; datacenters; quality-of-service; resource management; serverless
A22: WWM2ZLJL | B22: conferencePaper | C22: 2022 | D22: Ca√±ete, Angel; Rodr√≠guez, Alberto; Amor, Mercedes; Fuentes, Lidia | E22: Energy-Aware Placement of&nbsp;Network Functions in&nbsp;Edge-Based Infrastructures with&nbsp;Open Source MANO and&nbsp;Kubernetes | F22: Service-Oriented Computing ‚Äì ICSOC 2022 Workshops: ASOCA, AI-PA, FMCIoT, WESOACS 2022, Sevilla, Spain, November 29 ‚Äì December 2, 2022 Proceedings | G22: 978-3-031-26506-8 | I22: 10.1007/978-3-031-26507-5_15 | J22: https://doi.org/10.1007/978-3-031-26507-5_15 | K22: 2022 | L22: 45734.379 | M22: 45734.379 | O22: 183‚Äì195 | Z22: Springer-Verlag | AA22: Berlin, Heidelberg | AI22: event-place: Seville, Spain | CL22: The virtualization of network functions aims to replace traditional network functions running on proprietary middleboxes with software instances running on general-purpose virtualization solutions, looking for more flexible, scalable and sustainable networks. However, despite the availability of platforms and technologies that enable its realisation, there are still technical challenges that have to be addressed to obtain those benefits. One of the challenges is the efficient placement of network functions, considering, for instance, the energy footprint among other constraints and available resources. This paper proposes an energy-aware virtual network function placement and resource-allocation solution for heterogeneous edge infrastructures that considers the computation and communication delays according to the virtual network functions‚Äô location in the infrastructure. The solution has been integrated with the ETSI-sponsored project Open Source Management and Orchestration (OSM) as an extension that allows the configuration of virtual network functions and their subsequent resource allocation and deployment at the edge, minimizing energy consumption and ensuring the quality of service. Applied to the deployment of augmented reality services in different scenarios, the results show up to a 51% reduction in energy consumption compared to the default OSM placement and quality of service compliance in all scenarios considered. | DL22: Energy efficiency; Edge computing; B5G; Feature models; Open source mano; VNF placement
A23: 4L2TTRXF | B23: conferencePaper | C23: 2019 | D23: Nguyen, Chanh; Mehta, Amardeep; Klein, Cristian; Elmroth, Erik | E23: Why cloud applications are not ready for the edge (yet) | F23: Proceedings of the 4th ACM/IEEE Symposium on Edge Computing | G23: 978-1-4503-6733-2 | I23: 10.1145/3318216.3363298 | J23: https://doi.org/10.1145/3318216.3363298 | K23: 2019 | L23: 45734.379 | M23: 45734.379 | O23: 250‚Äì263 | V23: SEC '19 | Z23: Association for Computing Machinery | AA23: New York, NY, USA | AI23: event-place: Arlington, Virginia | CL23: Mobile Edge Clouds (MECs) are distributed platforms in which distant data-centers are complemented with computing and storage capacity located at the edge of the network. Their wide resource distribution enables MECs to fulfill the need of low latency and high bandwidth to offer an improved user experience.As modern cloud applications are increasingly architected as collections of small, independently deployable services, they can be flexibly deployed in various configurations that combines resources from both centralized datacenters and edge locations. In principle, such applications should therefore be well-placed to exploit the advantages of MECs so as to reduce service response times.In this paper, we quantify the benefits of deploying such cloud micro-service applications on MECs. Using two popular benchmarks, we show that, against conventional wisdom, end-to-end latency does not improve significantly even when most application services are deployed in the edge location. We developed a profiler to better understand this phenomenon, allowing us to develop recommendations for adapting applications to MECs. Further, by quantifying the gains of those recommendations, we show that the performance of an application can be made to reach the ideal scenario, in which the latency between an edge datacenter and a remote datacenter has no impact on the application performance.This work thus presents ways of adapting cloud-native applications to take advantage of MECs and provides guidance for developing MEC-native applications. We believe that both these elements are necessary to drive MEC adoption. | DL23: edge latency; micro-service; mobile application development; mobile edge clouds; profiling
A24: DNTRKNEN | B24: conferencePaper | C24: 2022 | D24: Zilic, Josip; De Maio, Vincenzo; Aral, Atakan; Brandic, Ivona | E24: Edge offloading for microservice architectures | F24: Proceedings of the 5th International Workshop on Edge Systems, Analytics and Networking | G24: 978-1-4503-9253-2 | I24: 10.1145/3517206.3526266 | J24: https://doi.org/10.1145/3517206.3526266 | K24: 2022 | L24: 45734.379 | M24: 45734.379 | O24: 1‚Äì6 | V24: EdgeSys '22 | Z24: Association for Computing Machinery | AA24: New York, NY, USA | AI24: event-place: Rennes, France | CL24: Edge offloading is widely used to support the execution of near real-time mobile applications. However, offloading on edge infrastructures can suffer from failures due to the absence of supporting systems and environmental factors. We propose a fault-tolerant offloading method modeled as a Markov Decision Process (MDP) based on predictions performed through Support Vector Regression (SVR). SVR is used to estimate offloading service availability, which is used by MDP for offloading decisions. Our approach is implemented in a real-world test-bed and compared with the default Kubernetes scheduler augmented with hybrid fault-tolerance. | DL24: microservices; kubernetes; containers; edge offloading
A25: BMPKCL2U | B25: conferencePaper | C25: 2024 | D25: Aissat, Sara; Beaulieu, Jonathan; Bordeleau, Francis; Gascon-Samson, Julien; Poirier, Erik A.; Motamedi, Ali | E25: JuNo-OPS: A DevOps Framework for the Engineering of Digital Twins for Built Assets | F25: Proceedings of the ACM/IEEE 27th International Conference on Model Driven Engineering Languages and Systems | G25: 979-8-4007-0622-6 | I25: 10.1145/3652620.3688266 | J25: https://doi.org/10.1145/3652620.3688266 | K25: 2024 | L25: 45734.379 | M25: 45734.379 | O25: 496‚Äì506 | V25: MODELS Companion '24 | Z25: Association for Computing Machinery | AA25: New York, NY, USA | AI25: event-place: Linz, Austria | CL25: Digital Twins (DT) constitute complex software systems that need to be continuously modified/updated to meet evolving user requirements and priorities, and support continual improvement. Because they aim at monitoring and improving different system aspects, their development requires the collaboration of people from different domains of expertise, e.g. the development of a DT for built assets may involve the collaboration of experts in software engineering, thermal comfort, air quality, and energy consumption, etc. Consequently, DTs need to be engineered to enable the fast and secure integration and deployment of new code, the systematic and iterative evolution of their components, and the independent development of different system aspects by those experts.In this paper, we present JuNo-OPS, a DevOps framework for the engineering of DTs for built assets. The framework is being developed, tested and validated in the the context of a multi-function room at √âcole de Technologie Sup√©rieure (ETS). We focus on two main facets of the DT software: the microservices architecture; and the DevOps infrastructure used to support the development, continuous integration, continuous delivery and the automation thereof. We also discuss challenges and next steps related to the development and evolution of the framework. | DL25: digital twins; microservices; DevOps; IoT; CI/CD pipelines
A26: 4J4KC6TP | B26: conferencePaper | C26: 2024 | D26: Ordonez, Carlos; Macyna, Wojciech; Bellatreche, Ladjel | E26: Energy-Aware Analytics in the Cloud | F26: Proceedings of the International Workshop on Big Data in Emergent Distributed Environments | G26: 979-8-4007-0679-0 | I26: 10.1145/3663741.3664789 | J26: https://doi.org/10.1145/3663741.3664789 | K26: 2024 | L26: 45734.379 | M26: 45734.379 | V26: BiDEDE '24 | Z26: Association for Computing Machinery | AA26: New York, NY, USA | AI26: event-place: Santiago, AA, Chile | CL26: Big data is now mostly processed in the cloud and will keep growing, fed by databases and the Internet of Things (IoT: sensors, mobile devices, edge computing). On the other hand, AI is pushing computers and data analysis to limits we had not witnessed before. Analytics in the cloud is now a major fraction of energy consumption, among other less CPU-intensive tasks like web services. With this green computing motivation in mind, we present a survey of past research and a vision of big data analytics in the cloud. Energy consumption is difficult to minimize because it has conflicting correlated variables behind: high performance, money cost and pollution, We identify which software subsystems and hardware components have a higher impact on energy consumption, understanding how they can be tweaked or tuned to optimize energy consumption.
A27: X4IGCSFQ | B27: conferencePaper | C27: 2024 | D27: Vaidhyanathan, Karthik; Caporuscio, Mauro; Florio, Stefano; Muccini, Henry | E27: ML-enabled Service Discovery for Microservice Architecture: a QoS Approach | F27: Proceedings of the 39th ACM/SIGAPP Symposium on Applied Computing | G27: 979-8-4007-0243-3 | I27: 10.1145/3605098.3635942 | J27: https://doi.org/10.1145/3605098.3635942 | K27: 2024 | L27: 45734.379 | M27: 45734.379 | O27: 1193‚Äì1200 | V27: SAC '24 | Z27: Association for Computing Machinery | AA27: New York, NY, USA | AI27: event-place: Avila, Spain | CL27: Microservice architectures have gained enormous popularity due to their ability to be dynamically added/removed, replicated, and updated according to run-time needs. However, the dynamic nature of microservices introduces uncertainty, which in turn can affect the provided Quality of Service (QoS). This calls for novel service discovery mechanisms able to adapt to the variability of the QoS attributes and further perform effective service discovery and selection. To this end, this paper combines machine learning and self-adaptation techniques to perform service discovery and selection by trading off different QoS attributes. The results of our validation on a state-of-the-art microservices exemplar show that our ML-enabled approach can perform service discovery with 35% higher effectiveness with respect to existing baselines. | DL27: machine learning; self-adaptation; service discovery
A28: EUN8J4KM | B28: conferencePaper | C28: 2016 | D28: Carrega, A.; Repetto, M. | E28: Exploiting novel software development paradigms to increase the sustainability of data centers | F28: Proceedings of the 9th International Conference on Utility and Cloud Computing | G28: 978-1-4503-4616-0 | I28: 10.1145/2996890.3007878 | J28: https://doi.org/10.1145/2996890.3007878 | K28: 2016 | L28: 45734.379 | M28: 45734.379 | O28: 310‚Äì315 | V28: UCC '16 | Z28: Association for Computing Machinery | AA28: New York, NY, USA | AI28: event-place: Shanghai, China | CL28: The application of effective energy management strategies in data centers is often hindered by the substantial conflict between the interests of cloud users and infrastructure owners. As a matter of fact, cloud users require that the service level they are paying for is tightly met, whereas data center owners try to cut down their operational expenses.In this paper, we propose a novel consolidation algorithm that exploits emerging software development paradigms. Our approach enables cloud users to indicate their willingness to apply energy saving mechanisms to some of their virtual resources, hence giving infrastructure managers the ability to apply more efficient workload consolidation and to switch their hardware to very low-power states. The result is an optimal trade-off between energy consumption and performance. | DL28: energy efficiency; consolidation algorithms; green data centers; software development paradigms
A29: ULZWPBSI | B29: conferencePaper | C29: 2024 | D29: Chow, Ka-Ho; Deshpande, Umesh; Deenadayalan, Veera; Seshadri, Sangeetha; Liu, Ling | E29: Atlas: Hybrid Cloud Migration Advisor for Interactive Microservices | F29: Proceedings of the Nineteenth European Conference on Computer Systems | G29: 979-8-4007-0437-6 | I29: 10.1145/3627703.3629587 | J29: https://doi.org/10.1145/3627703.3629587 | K29: 2024 | L29: 45734.379 | M29: 45734.379 | O29: 870‚Äì887 | V29: EuroSys '24 | Z29: Association for Computing Machinery | AA29: New York, NY, USA | AI29: event-place: Athens, Greece | CL29: Hybrid cloud provides an attractive solution to microservices for better resource elasticity. A subset of application components can be offloaded from the on-premises cluster to the cloud, where they can readily access additional resources. However, the selection of this subset is challenging because of the large number of possible combinations. A poor choice degrades the application performance, disrupts the critical services, and increases the cost to the extent of making the use of hybrid cloud unviable. This paper presents Atlas, a hybrid cloud migration advisor. Atlas uses a data-driven approach to learn how each user-facing API utilizes different components and their network footprints to drive the migration decision. It learns to accelerate the discovery of high-quality migration plans from millions and offers recommendations with customizable trade-offs among three quality indicators: end-to-end latency of user-facing APIs representing application performance, service availability, and cloud hosting costs. Atlas continuously monitors the application even after the migration for proactive recommendations. Our evaluation shows that Atlas can achieve 21% better API performance (latency) and 11% cheaper cost with less service disruption than widely used solutions. | DL29: placement; microservices; machine learning; API; cyberattacks; hybrid cloud
A30: AASHMHM3 | B30: conferencePaper | C30: 2019 | D30: Mehran, Narges; Kimovski, Dragi; Prodan, Radu | E30: MAPO: A Multi-Objective Model for IoT Application Placement in a Fog Environment | F30: Proceedings of the 9th International Conference on the Internet of Things | G30: 978-1-4503-7207-7 | I30: 10.1145/3365871.3365892 | J30: https://doi.org/10.1145/3365871.3365892 | K30: 2019 | L30: 45734.379 | M30: 45734.379 | V30: IoT '19 | Z30: Association for Computing Machinery | AA30: New York, NY, USA | AI30: event-place: Bilbao, Spain | CL30: The emergence of the Fog computing paradigm that leverages innetwork virtualized resources raises important challenges in terms of resource and IoT application management in a heterogeneous environment with limited computing resources. In this work, we propose a novel Pareto-based approach for application placement close to the data sources called Multi-objective IoT Application Placement in fOg (MAPO). MAPO models applications based on a finite state machine using three conflicting optimization objectives, completion time, energy consumption, and economic cost, and considering both the computation and communication aspects. In contrast to existing solutions that optimize a single objective, MAPO enables multi-objective energy and cost-aware application placement. To evaluate the quality of the MAPO placements, we created both simulated and real-world testbeds tailored for a set of medical IoT application case studies. Compared to the state-of-the-art approaches, MAPO reduces the economic cost by 28%, while decreasing the energy requirements by 29-64% on average, and improves the completion time by a factor of six. | DL30: energy consumption; Fog computing; IoT application placement; multi-objective optimization
A31: QBK9JZ3F | B31: conferencePaper | C31: 2024 | D31: Reitzl, Marcus; Kimovski, Dragi | E31: Multi-Objective Optimisation of Container Orchestration Systems | F31: Proceedings of the IEEE/ACM 16th International Conference on Utility and Cloud Computing | G31: 979-8-4007-0234-1 | I31: 10.1145/3603166.3632536 | J31: https://doi.org/10.1145/3603166.3632536 | K31: 2024 | L31: 45734.379 | M31: 45734.379 | V31: UCC '23 | Z31: Association for Computing Machinery | AA31: New York, NY, USA | AI31: event-place: Taormina (Messina), Italy | CL31: The ever-increasing global demand for optimized resource utilization, energy efficiency, and rapid response times in cloud computing environments necessitates innovative approaches for resource management. Traditional cloud systems predominantly cater to large-scale infrastructures, often neglecting smaller-scale environments, such as edge computing infrastructures. In response to this gap, this paper introduces a novel Multi-Objective Stochastic Gradient Descent (MOSGD) approach designed to enhance the efficiency of the application placement processes beyond the cloud and closer to the edge of the network. The MOSGD optimisation addresses two crucial objectives: energy consumption and execution time. We meticulously modelled and integrated the two conflicting objectives into a unified cost function to minimise resource consumption and response time.To validate the MOSGD approach, we deployed a real-life environment utilizing the Carinthian Computing Continuum infrastructure as the target platform. The results of this research exhibit significant performance enhancements compared to two conventional methods. The findings indicate an improvement of up to 80% in energy efficiency and up to 30% reduction in execution time. These outcomes underscore the potential of the MOSGD approach to outperform traditional techniques in scenarios where large-scale procedures may exhibit suboptimal performance. | DL31: edge computing; optimisation; pod placement
A32: TWR9HA67 | B32: conferencePaper | C32: 2017 | D32: Munoz, Daniel-Jesus; Pinto, M√≥nica; Fuentes, Lidia | E32: Green software development and research with the HADAS toolkit | F32: Proceedings of the 11th European Conference on Software Architecture: Companion Proceedings | G32: 978-1-4503-5217-8 | I32: 10.1145/3129790.3129818 | J32: https://doi.org/10.1145/3129790.3129818 | K32: 2017 | L32: 45734.379 | M32: 45734.379 | O32: 205‚Äì211 | V32: ECSA '17 | Z32: Association for Computing Machinery | AA32: New York, NY, USA | AI32: event-place: Canterbury, United Kingdom | CL32: Energy is a critical resource, and designing a sustainable software architecture is a non-trivial task. Developers require energy metrics that support sustainable software architectures reflecting quality attributes such as security, reliability, performance, etc., identifying what are the concerns that impact more in the energy consumption. A variability model of different designs and implementations of an energy model should exist for this task, as well as a service that stores and compares the experimentation results of energy and time consumption of each concern, finding out what is the most eco-efficient solution. The experimental measurements are performed by energy experts and researchers that share the energy model and metrics in a collaborative repository. HADAS confronts these tasks modelling and reasoning with the variability of energy consuming concerns for different energy contexts, connecting HADAS variability model with its energy efficiency collaborative repository, establishing a Software Product Line (SPL) service. Our main goal is to help developers to perform sustainability analyses finding out the eco-friendliest architecture configurations. A HADAS toolkit prototype is implemented based on a Clafer model and Choco solver, and it has been tested with several case studies. | DL32: energy efficiency; variability; optimisation; clafer; CVL; metrics; repository; software product line
A33: YV3ESHUL | B33: conferencePaper | C33: 2023 | D33: Li, Bolun; Zhao, Qidong; Jiao, Shuyin; Liu, Xu | E33: DroidPerf: Profiling Memory Objects on Android Devices | F33: Proceedings of the 29th Annual International Conference on Mobile Computing and Networking | G33: 978-1-4503-9990-6 | I33: 10.1145/3570361.3592503 | J33: https://doi.org/10.1145/3570361.3592503 | K33: 2023 | L33: 45734.379 | M33: 45734.379 | V33: ACM MobiCom '23 | Z33: Association for Computing Machinery | AA33: New York, NY, USA | AI33: event-place: Madrid, Spain | CL33: Optimizing performance inefficiencies in memory hierarchies is well-known for native languages, such as C and C++. There are few studies, however, on exploring memory inefficiencies in Android Runtime (ART). Running in ART, managed languages, such as Java and Kotlin, employ various abstractions, such as runtime support, ahead-of-time (AOT) compilation, and garbage collection (GC), which hide important execution details from the plain source code.In this paper, we develop DroidPerf, a lightweight, object-centric memory profiler for ART, which associates memory inefficiencies with objects created and used in Android apps. With such object-level information, DroidPerf is able to guide locality optimization on memory layouts, access patterns, and allocation patterns. Guided by DroidPerf, we optimize a number of popular Android apps and obtain significant performance gains. Many inefficiencies are confirmed by the code authors and optimization patches are under evaluation for upstreaming. As a practical tool, DroidPerf incurs 32% runtime overhead and 14% memory overhead on average. Furthermore, DroidPerf works in the production environment with off-the-shelf hardware, OS, Dalvik virtual machine, ART, and unmodified Android app source code. | DL33: performance; profiling; Android; memory inefficiencies
A34: YHTMED3B | B34: conferencePaper | C34: 2024 | D34: El Akhdar, Abir; Baidada, Chafik; Kartit, Ali | E34: Adaptability of Microservices Architecture in IoT Systems : A Comprehensive Review | F34: Proceedings of the 7th International Conference on Networking, Intelligent Systems and Security | G34: 979-8-4007-0929-6 | I34: 10.1145/3659677.3659734 | J34: https://doi.org/10.1145/3659677.3659734 | K34: 2024 | L34: 45734.379 | M34: 45734.379 | V34: NISS '24 | Z34: Association for Computing Machinery | AA34: New York, NY, USA | AI34: event-place: Meknes, AA, Morocco | CL34: Abstract. This paper investigates how microservices, a transformative paradigm in cloud and enterprise applications, can adapt to the challenges presented by the Internet of Things (IoT). Microservices architecture, identified by the disintegration of monolithic software into distributed and decoupled services, presents a solution that enhances scalability and maintainability. While traditionally top-down, microservices align with IoT's need for flexible, vendor-independent service combinations. Identifying challenges in traditional IoT architectures, this research addresses a gap in the lack of a comprehensive review on the integration of microservices. Objectives include analyzing characteristics, identifying benefits and challenges, exploring best practices, and evaluating adaptability in terms of flexibility, scalability, data management, security, privacy, performance, and efficiency. We aim, through this work, to add to the existing knowledge base on microservices and IoT systems and offer valuable perspectives for practitioners and researchers in the field. | DL34: Microservices; Internet of Things; IoT; Software Architecture; MSA; Comprehensive Review
A35: HRJKWXL4 | B35: conferencePaper | C35: 2025 | D35: Truong, Thai Minh; Huynh, Khang Quy; Ngo, Thao Thi Thu; Luu, Ca; Le, Bang Minh | E35: The Microservice Based Architecture for IoT Systems in Agriculture and Aquaculture | F35: Proceedings of the 2024 14th International Conference on Information Communication and Management | G35: 979-8-4007-1747-5 | I35: 10.1145/3711609.3711613 | J35: https://doi.org/10.1145/3711609.3711613 | K35: 2025 | L35: 45734.379 | M35: 45734.379 | O35: 22‚Äì28 | V35: ICICM '24 | Z35: Association for Computing Machinery | AA35: New York, NY, USA | CL35: The rapid advancement of Internet of Things (IoT) technologies presents significant opportunities to enhance agriculture and aquaculture practices. This paper proposed a software architecture designed based on microservices to address the complex and evolving requirements of contemporary agriculture and aquaculture systems locations. These systems demand a versatile platform capable of integrating a wide range of functionalities, including environmental monitoring, aquaculture management, and comprehensive record-keeping for crops and aquatic life. The proposed IoT system employs a microservice architecture that ensures modularity, scalability, and flexibility. This approach facilitates the seamless integration of new services and features, easy adaptation to existing systems, and efficient reuse of established components. The microservice-based architecture has been successfully implemented in the TC2 project at Can Tho University under the Japan International Cooperation Agency (JICA) initiative. The project is in remote areas through the deployment of a network of sensor and actuator nodes, supported by a robust backend and user-friendly Front End applications. This implementation demonstrated notable improvements in operational efficiency and resource management. By leveraging edge computing for real-time data processing and integrating cloud-based analytics, the system achieved reduced response times and minimized data transmission costs. The modularity of the microservices architecture also enabled easy scalability and adaptability to change environmental conditions. The success of this implementation highlights the potential of microservices-based IoT solutions to drive innovation and enhance practices in agriculture and aquaculture, laying a strong foundation for future advancements in these fields. | DL35: Internet of Things (IoT); Microservices Architecture; Agriculture and Aquaculture
A36: BBGQX3GS | B36: conferencePaper | C36: 2022 | D36: Zandberg, Koen; Baccelli, Emmanuel; Yuan, Shenghao; Besson, Fr√©d√©ric; Talpin, Jean-Pierre | E36: Femto-containers: lightweight virtualization and fault isolation for small software functions on low-power IoT microcontrollers | F36: Proceedings of the 23rd ACM/IFIP International Middleware Conference | G36: 978-1-4503-9340-9 | I36: 10.1145/3528535.3565242 | J36: https://doi.org/10.1145/3528535.3565242 | K36: 2022 | L36: 45734.379 | M36: 45734.379 | O36: 161‚Äì173 | V36: Middleware '22 | Z36: Association for Computing Machinery | AA36: New York, NY, USA | AI36: event-place: Quebec, QC, Canada | CL36: Low-power operating system runtimes used on IoT microcontrollers typically provide rudimentary APIs, basic connectivity and, sometimes, a (secure) firmware update mechanism. In contrast, on less constrained hardware, networked software has entered the age of serverless, microservices and agility. With a view to bridge this gap, in the paper we design Femto-Containers, a new middleware runtime which can be embedded on heterogeneous low-power IoT devices. Femto-Containers enable the secure deployment, execution and isolation of small virtual software functions on low-power IoT devices, over the network. We implement Femto-Containers, and provide integration in RIOT, a popular open source IoT operating system. We then evaluate the performance of our implementation, which was formally verified for fault-isolation, guaranteeing that RIOT is shielded from logic loaded and executed in a Femto-Container. Our experiments on various popular micro-controller architectures (Arm Cortex-M, ESP32 and RISC-V) show that Femto-Containers offer an attractive trade-off in terms of memory footprint overhead, energy consumption, and security. | DL36: security; IoT; middleware; container; function-as-a-service; low-power; microcontroller; virtual machine
A37: 43F6H3KN | B37: conferencePaper | C37: 2024 | D37: Sedlak, Boris; Morichetta, Andrea; Wang, Yuhao; Fei, Yang; Wang, Liang; Dustdar, Schahram; Qu, Xiaobo | E37: SLO-Aware Task Offloading Within Collaborative Vehicle Platoons | F37: Service-Oriented Computing: 22nd International Conference, ICSOC 2024, Tunis, Tunisia, December 3‚Äì6, 2024, Proceedings, Part II | G37: 978-981-96-0807-2 | I37: 10.1007/978-981-96-0808-9_6 | J37: https://doi.org/10.1007/978-981-96-0808-9_6 | K37: 2024 | L37: 45734.379 | M37: 45734.379 | O37: 72‚Äì86 | Z37: Springer-Verlag | AA37: Berlin, Heidelberg | AI37: event-place: Tunis, Tunisia | CL37: In the context of autonomous vehicles (AVs), offloading is essential for guaranteeing the execution of perception tasks, e.g., mobile mapping or object detection. While existing work on offloading focused extensively on minimizing inter-vehicle networking latency, vehicle platoons (e.g., heavy-duty transport) present numerous other objectives, such as energy efficiency or data quality. To optimize these Service Level Objectives (SLOs) during operation, this work presents a purely Vehicle-to-Vehicle approach (V2V) for collaborative services offloading within a vehicle platoon. By training and using a Bayesian Network (BN), services can proactively decide to offload whenever this promises to improve platoon-wide SLO fulfillment; therefore, vehicles estimate how both sides would be impacted by offloading a service. In particular, this considers resource heterogeneity within the platoon to avoid overloading more restricted devices. We evaluate our approach in a physical setup, where vehicles in a platoon continuously (i.e., every 500 ms) interpret the SLOs of three perception services. Our probabilistic, predictive method shows promising results in handling large AV platoons; within seconds, it detects and resolves SLO violations through offloading. | DL37: Microservices; Edge Computing; Bayesian Networks; Intelligent Transportation; Offloading; Service Level Objectives
A38: 87YFBPKY | B38: conferencePaper | C38: 2022 | D38: Vitali, Monica | E38: Towards Greener Applications: Enabling Sustainable-aware Cloud Native Applications Design | F38: Advanced Information Systems Engineering: 34th International Conference, CAiSE 2022, Leuven, Belgium, June 6‚Äì10, 2022, Proceedings | G38: 978-3-031-07471-4 | I38: 10.1007/978-3-031-07472-1_6 | J38: https://doi.org/10.1007/978-3-031-07472-1_6 | K38: 2022 | L38: 45734.379 | M38: 45734.379 | O38: 93‚Äì108 | Z38: Springer-Verlag | AA38: Berlin, Heidelberg | AI38: event-place: Leuven, Belgium | CL38: Data centers energy demand is increasing. While a great deal of effort has been made to reduce the amount of CO2 generated by large cloud providers, too little has been done from the application perspective. We claim that application developers can impact the environmental footprint by enhancing the application design with additional features. Following the proposed Sustainable Application Design Process (SADP), the application design is enriched with information that can be leveraged by cloud providers to manage application execution in an energy-aware manner. This exploratory work aims to emphasize the awareness on the sustainability of applications by proposing a methodology for its evaluation. To this end, we first suggest possible actions to enrich the application design towards sustainability, and finally describe how this additional information can be leveraged in the application workflow. We discuss the feasibility of our methodology by referring to existing tools and technologies capable of supporting the design features proposed in a production environment. | DL38: Cloud-native; Energy-efficiency; Sustainability-awareness; Sustainable applications; Workflow design
A39: ZEERA26W | B39: conferencePaper | C39: 2018 | D39: Vu, Tran Hoang; Dai, Nghia Hoang Ba; Khanh, Hong Nguyen Thi; Quang, Dong Nguyen Vo | E39: Overall Structural System Solution for Supporting Services and Tourists Management Oriented on Smart City in Viet Nam | F39: Proceedings of the 9th International Symposium on Information and Communication Technology | G39: 978-1-4503-6539-0 | I39: 10.1145/3287921.3287966 | J39: https://doi.org/10.1145/3287921.3287966 | K39: 2018 | L39: 45734.379 | M39: 45734.379 | O39: 430‚Äì435 | V39: SoICT '18 | Z39: Association for Computing Machinery | AA39: New York, NY, USA | AI39: event-place: Danang City, Viet Nam | CL39: Recently, "Smart tourism" has appeared as a new term to describe the application of the technological advancements that rely on sensors, big data processing technique, open data, open API, new way of connecting and exchanging between humans and machines and multi-device (such as IoT, RFID, and NFC) in tourism. When these technologies are utilized, the digital data become practical and valuable products. Besides, the mobile revolution, and specifically the role of the smartphone and its many opportunities to support travel experiences, is especially worth mentioning in this context. In addition, new management tool for the government, new business opportunities for travel agencies, as well as new experiences for tourists are created. Therefore, in this paper, a model for developing sustainable and intelligent tourism is studied and then an overall architecture model of the information system that can provide supporting services and tools for visitor management (Smart Tourism Service Centre ‚Äì STSC) is proposed for fostering the smart cities in Vietnam, in general, and Danang, in particular. | DL39: IoT; Smart city; Micro-Services; NFC; Smart Tourism
A40: D3EUITD8 | B40: conferencePaper | C40: 2024 | D40: Chen, Li; Wang, Hai; Hou, Fuyuan; Li, Biao; Zhang, Wangli | E40: Research on the Security of Internet of Things Based on Microservices Techniques | F40: Proceedings of the 2023 3rd International Conference on Big Data, Artificial Intelligence and Risk Management | G40: 979-8-4007-1647-8 | I40: 10.1145/3656766.3656853 | J40: https://doi.org/10.1145/3656766.3656853 | K40: 2024 | L40: 45734.379 | M40: 45734.379 | O40: 509‚Äì516 | V40: ICBAR '23 | Z40: Association for Computing Machinery | AA40: New York, NY, USA | AI40: event-place: Chengdu, China | CL40: Internet of Things technology refers to connecting different types of physical devices, sensors, and other devices together through the Internet to achieve real-time data exchange, thereby achieving real-time monitoring and data analysis. With the continuous development of internet technology, the IoT technology is becoming an important component of future smart homes, smart cities, and Industry 4.0 fields. There are multiple communication protocols and data formats between IoT devices, and a large number of monolithic structures lead to issues such as insufficient scalability and flexibility, resulting in a large number of security vulnerabilities in IoT communication, threatening network security and data privacy. Microservices technology splits a single application into multiple small services that run in separate processes, using lightweight communication mechanisms between services. The interaction between microservices uses standard communication technology, which can enhance the scalability and security of IoT device applications. This article proposes a microservice based security access model that enables fine-grained access decisions, effectively reducing attacks related to IoT device connections and data security, and providing scalable, reconfigurable, and reusable security services. We analyzed the feasibility, reliability, and efficiency of the proposed scheme through theoretical analysis and experiments. The CPU and memory usage of microservices was tested, as well as microservices concurrency performance. The experimental results show that the proposed microservices can achieve corresponding functions and return device data. The microservice scheme designed in this article can meet normal access requests and security communication.
A41: VBBYNP2F | B41: conferencePaper | C41: 2023 | D41: Chochliouros, Ioannis P.; Pages-Montanera, Enric; Alc√°zar-Fern√°ndez, Aitor; Zahariadis, Theodore; Velivassaki, Terpsichori-Helen; Skianis, Charalabos; Rossini, Rosaria; Belesioti, Maria; Drosos, Nikolaos; Bakiris, Emmanouil; Pedholla, Prashanth Kumar; Karkazis, Panagiotis; Samal, Astik Kumar; Contreras Murillo, Luis Miguel; Del R√≠o, Alberto; Serrano, Javier; Skias, Dimitrios; Segou, Olga E.; Waechter, Sonja | E41: NEMO: Building the Next Generation Meta Operating System | F41: Proceedings of the 3rd Eclipse Security, AI, Architecture and Modelling Conference on Cloud to Edge Continuum | G41: 979-8-4007-0835-0 | I41: 10.1145/3624486.3624504 | J41: https://doi.org/10.1145/3624486.3624504 | K41: 2023 | L41: 45734.379 | M41: 45734.379 | O41: 1‚Äì9 | V41: eSAAM '23 | Z41: Association for Computing Machinery | AA41: New York, NY, USA | AI41: event-place: Ludwigsburg, Germany | CL41: Artificial Intelligence of Things (AIoT) is one of the next big concepts to support societal changes and economic growth, being one of the fastest growing ICT segments. A specific challenge is to leverage existing technology strengths to develop solutions that sustain the European industry and values. The ongoing ŒùŒïŒúŒü (‚ÄúNext Generation Meta-Operating System‚Äù) EU-funded project intends to establish itself as the ‚Äúgame changer‚Äù of the AIoT-Edge-Cloud continuum by introducing an open source, modular and cybersecure meta-operating system, leveraging on existing technologies and introducing novel concepts, methods, tools, testing and engagement campaigns.NEMO will bring intelligence closer to the data and make AI-as-a-Service an integral part of network self-organisation and micro-services execution orchestration. Its widespread penetration and massive acceptance will be achieved via new technology, pre-commercial exploitation components and liaison with open-source communities.By defining a modular and adaptable mOS (meta-OS) architecture together with building blocks and plugins the project will ‚Äúaddress‚Äù current and future technological and business needs. | DL41: Artificial Intelligence of Things; Meta Operating system; The Cloud-to-Thing continuum: opportunities and challenges
A42: M9BY5WNT | B42: conferencePaper | C42: 2017 | D42: Hasan, MD Sabbir; Alvares, Frederico; Ledoux, Thomas | E42: GPaaScaler: Green Energy Aware Platform Scaler for Interactive Cloud Application | F42: Proceedings of The10th International Conference on Utility and Cloud Computing | G42: 978-1-4503-5149-2 | I42: 10.1145/3147213.3147227 | J42: https://doi.org/10.1145/3147213.3147227 | K42: 2017 | L42: 45734.379 | M42: 45734.379 | O42: 79‚Äì89 | V42: UCC '17 | Z42: Association for Computing Machinery | AA42: New York, NY, USA | AI42: event-place: Austin, Texas, USA | CL42: Recently, smart usage of renewable energy has been a hot topic in the Cloud community. In this vein, we have recently proposed the creation of green energy awareness around Interactive Cloud Applications, but in static amount of underlying resources. This paper adds to previous ones as it considers elastic underlying infrastructure, that is, we propose a PaaS solution which efficiently utilize the elasticity nature at both infrastructure and application levels, by leveraging adaptation in facing to changing condition i.e., workload burst, performance degradation, quality of energy, etc. While applications are adapted by dynamically re-configuring their service level based on performance and/or green energy availability, the infrastructure takes care of addition/removal of resources based on application's resource demand. Both adaptive behaviors are implemented in separated modules and are coordinated in a sequential manner.We validate our approach by extensive experiments and results obtained over Grid'5000 test bed. Results show that, application can reduce significant amount of brown energy consumption by 35% and daily instance hour cost by 37% compared to a baseline approach when green energy aware adaptation is considered. | DL42: energy consumption; autonomic computing; green it; interactive cloud application; paas; sustainable computing.
A43: QNXBMJ6P | B43: conferencePaper | C43: 2023 | D43: Aldinucci, Marco; Baralis, Elena Maria; Cardellini, Valeria; Colonnelli, Iacopo; Danelutto, Marco; Decherchi, Sergio; Di Modica, Giuseppe; Ferrucci, Luca; Gribaudo, Marco; Iannone, Francesco; Lapegna, Marco; Medic, Doriana; Muscianisi, Giuseppa; Righetti, Francesca; Sciacca, Eva; Tonellotto, Nicola; Tortonesi, Mauro; Trunfio, Paolo; Vardanega, Tullio | E43: A Systematic Mapping Study of Italian Research on Workflows | F43: Proceedings of the SC '23 Workshops of the International Conference on High Performance Computing, Network, Storage, and Analysis | G43: 979-8-4007-0785-8 | I43: 10.1145/3624062.3624285 | J43: https://doi.org/10.1145/3624062.3624285 | K43: 2023 | L43: 45734.379 | M43: 45734.379 | O43: 2065‚Äì2076 | V43: SC-W '23 | Z43: Association for Computing Machinery | AA43: New York, NY, USA | AI43: event-place: Denver, CO, USA | CL43: An entire ecosystem of methodologies and tools revolves around scientific workflow management. They cover crucial non-functional requirements that standard workflow models fail to target, such as interactive execution, energy efficiency, performance portability, Big Data management, and intelligent orchestration in the Computing Continuum. Characterizing and monitoring this ecosystem is crucial to developing an informed view of current and future research directions. This work conducts a systematic mapping study of the Italian workflow research community, analyzing 25 tools and 10 applications from several scientific domains in the context of the "National Research Centre for HPC, Big Data, and Quantum Computing" (ICSC). The study aims to outline the main current research directions and determine how they address the critical needs of modern scientific applications. The findings highlight a variegated research ecosystem of tools, with a prominent interest in advanced workflow orchestration and still immature but promising efforts toward energy efficiency. | DL43: Computing Continuum; HPC; Scientific Workflows
A44: 9RCNRBIM | B44: conferencePaper | C44: 2021 | D44: Ghorbani, Mohammadmahdi; Moghaddam, Fereydoun Farrahi; Zhang, Mengyuan; Pourzandi, Makan; Nguyen, Kim Khoa; Cheriet, Mohamed | E44: DistAppGaurd: Distributed Application Behaviour Profiling in Cloud-Based Environment | F44: Proceedings of the 37th Annual Computer Security Applications Conference | G44: 978-1-4503-8579-4 | I44: 10.1145/3485832.3485907 | J44: https://doi.org/10.1145/3485832.3485907 | K44: 2021 | L44: 45734.379 | M44: 45734.379 | O44: 837‚Äì848 | V44: ACSAC '21 | Z44: Association for Computing Machinery | AA44: New York, NY, USA | AI44: event-place: Virtual Event, USA | CL44: Today, Machine Learning (ML) techniques are increasingly used to detect abnormal behaviours of industrial applications. Since many of these applications are moving to the cloud environments, classical ML approaches are facing new challenges in accurately identifying abnormal behaviours due to the highly dynamic and heterogeneous nature of the cloud. In this paper, we propose a novel framework, DistAppGaurd, for profiling simultaneously the behaviour of all microservice components of a distributed application in the cloud. The framework can therefore, detect complex attacks that are not observable by monitoring a single process or a single microservice. DistAppGaurd utilizes the system calls executed by all the processes of an application to build a graph consisting of data exchanges among different application entities (e.g., processes and files) representing the behaviour of the application. This representation is then used by our novel miroservice-aware Autoencoder model to perform anomaly detection at runtime. The efficiency and feasibility of our approach is shown by implementing several different real-world attacks, which yields high detection rates (94%-97%) at 0.01% false alarm rate. | DL44: anomaly detection; microservice; machine learning; autoencoder; distributed behaviour profiling
A45: JVT2ZT9I | B45: conferencePaper | C45: 2023 | D45: He, Xiang; Shao, Zihao; Wang, Teng; Shi, Haomai; Chen, Yin; Wang, Zhongjie | E45: Predicting Effect and Cost of Microservice System Evolution Using Graph Neural Network | F45: Service-Oriented Computing: 21st International Conference, ICSOC 2023, Rome, Italy, November 28 ‚Äì December 1, 2023, Proceedings, Part I | G45: 978-3-031-48420-9 | I45: 10.1007/978-3-031-48421-6_8 | J45: https://doi.org/10.1007/978-3-031-48421-6_8 | K45: 2023 | L45: 45734.379 | M45: 45734.379 | O45: 103‚Äì118 | Z45: Springer-Verlag | AA45: Berlin, Heidelberg | AI45: event-place: Rome, Italy | CL45: With the increasing prevalence of microservice technology, the architectural flexibility and scalability of software systems have witnessed notable advancements. However, this progress has also brought about a challenge in meeting the frequent changes in user requirements, thereby adversely affecting the quality of the system. It is crucial for microservice systems to undergo evolution through the modification of system configurations to adapt to changing requirements, and various methods for system evolution have been proposed. However, the evolution schemes generated by these methods vary in terms of the degree of improvement in quality and the cost required for evolution, such as time and money, i.e., different evolution effect and evolution cost. Considering the above, it is necessary to predict effect and cost before applying these schemes to real systems. Existing physical methods possess drawbacks such as high expenses and time-consuming setup procedures. Conversely, simulation methods, which are based on mathematical models, necessitate certain simplifications, resulting in disparities between the outcomes and the actual results. To overcome these challenges, this paper introduces a prediction method for microservice system evolution. By employing Graph Neural Network techniques to learn from historical data, this method enables precise prediction of the effects and costs associated with various microservice evolution schemes. And based on the above algorithm, an online prediction system is implemented, independent of the microservice system for long-term prediction. Experimental results validate the accuracy and robustness of the proposed prediction method. | DL45: Prediction; Evolution Cost; Evolution Effect; Microservice system
A46: 95WDRTJW | B46: conferencePaper | C46: 2024 | D46: Morales, Jose; Antunes, Luiz; Earl, Patrick; Edman, Robert; Hamed, Jeffrey; Reynolds, Douglas; Maffey, Katherine R; Yankel, Joseph; Yasar, Hasan | E46: Insights on Implementing a Metrics Baseline for Post-Deployment AI Container Monitoring | F46: Proceedings of the 2024 International Conference on Software and Systems Processes | G46: 979-8-4007-0991-3 | I46: 10.1145/3666015.3666018 | J46: https://doi.org/10.1145/3666015.3666018 | K46: 2024 | L46: 45734.379 | M46: 45734.379 | O46: 46‚Äì55 | V46: ICSSP '24 | Z46: Association for Computing Machinery | AA46: New York, NY, USA | AI46: event-place: M\, Germany | CL46: Post-deployment monitoring (PDM) occurs in the late stages of a DevSecOps (DSO) pipeline. Its role in DSO is critical in providing feedback loops on system performance leading to desirable changes achieving long-term system and application sustainment. Containers are the de-facto deployed artifacts in DSO for diverse forms of systems and applications including AI models. Long-term sustainment of containerized AI models requires appropriate metrics for the successful maintenance of optimal container and model computing performance and correct model inference. There is no agreed upon set of metrics that should always be present when monitoring a deployed containerized AI model. The current literature and practice can benefit from a standard baseline of metrics for long-term monitoring of containerized AI models focused on computing and inference. In this paper, we propose a candidate baseline of metrics for consideration as a standard across PDM for any containerized AI model. We present a proof-of-concept (PoC) that implements a baseline of metrics for the continuous monitoring of an operationally deployed containerized AI model. The baseline represents the minimal metrics required for any containerized model deployed and actively operating to ensure successful long-term monitoring and support of optimal operation and performance. The metrics focus on container operation, model operation, and model inference. This paper also details the raw data required for the metrics along with a PoC which demonstrates container engineering for their acquisition. The paper illustrates the baseline as a mix of dynamic metrics that are customized for each problem class (e.g., object detection, regression) and data modality together with static metrics that should be present for any containerized model. The paper further shows that a containerized AI model can be engineered to produce these metrics and describes the benefits of a standardized baseline of metrics to aid in the reduction of power consumption in the global digital enterprise. | DL46: AI; Artificial Intelligence; Container; Continuous Deployment; Deployment; DevOps; DevSecOps.; Machine Learning; Metrics; ML; Performance
A47: AH39I8JA | B47: conferencePaper | C47: 2022 | D47: N. Toosi, Adel; Agarwal, Chayan; Mashayekhy, Lena; Moghaddam, Sara K.; Mahmud, Redowan; Tari, Zahir | E47: GreenFog: A Framework for&nbsp;Sustainable Fog Computing | F47: Service-Oriented Computing: 20th International Conference, ICSOC 2022, Seville, Spain, November 29 ‚Äì December 2, 2022, Proceedings | G47: 978-3-031-20983-3 | I47: 10.1007/978-3-031-20984-0_38 | J47: https://doi.org/10.1007/978-3-031-20984-0_38 | K47: 2022 | L47: 45734.379 | M47: 45734.379 | O47: 540‚Äì549 | Z47: Springer-Verlag | AA47: Berlin, Heidelberg | AI47: event-place: Seville, Spain | CL47: The alarming rate of increase in energy demand and carbon footprint of Fog environments has become a critical issue. It is, therefore, necessary to reduce the percentage of brown energy consumption in these systems and integrate renewable energy use into Fog. Renewables, however, are prone to availability fluctuations due to their variable and intermittent nature. In this paper, we propose a new Fog framework and design various optimization techniques, including linear programming optimization, linear regression estimation, and Multi-Armed Bandit (MAB) learning to optimize renewable energy use in the Fog based on a novel idea of load shaping with adaptive Quality of Service (QoS). The proposed framework, along with the optimization techniques, are tested on a real-world micro data center (Fog environment) powered by solar energy sources connected to multiple IoT devices. The results show that our proposed framework significantly reduces the difference between renewable energy generation and total energy consumption while efficiently adjusting the QoS of applications.
A48: DD4XQV9A | B48: conferencePaper | C48: 2021 | D48: Rao, Vishal; Singh, Vishnu; Goutham, K. S.; Kempaiah, Bharani Ujjaini; Mampilli, Ruben John; Kalambur, Subramaniam; Sitaram, Dinkar | E48: Scheduling Microservice Containers on Large Core Machines Through Placement and Coalescing | F48: Job Scheduling Strategies for Parallel Processing: 24th International Workshop, JSSPP 2021, Virtual Event, May 21, 2021, Revised Selected Papers | G48: 978-3-030-88223-5 | I48: 10.1007/978-3-030-88224-2_5 | J48: https://doi.org/10.1007/978-3-030-88224-2_5 | K48: 2021 | L48: 45734.379 | M48: 45734.379 | O48: 80‚Äì100 | Z48: Springer-Verlag | AA48: Berlin, Heidelberg | CL48: Current applications deployed on the cloud use the microservice programming model to enable rapid deployment. Due to the loosely coupled nature of the interactions between microservices, they are well suited for the distributed nature of cloud systems. However, we are seeing a trend of increasing core counts on newer server hardware and scheduling microservices agnostic to the local organization of cores and memory on these systems leads to sub-optimal performance. In this paper, we propose a placement scheme to map containers of a microservice to various cores on such machines to maximize performance. We further study the impact of various parameters such as packet sizes and database sizes on the placement scheme and demonstrate that our placement scheme increases throughput by 22% while simultaneously lowering tail latency. Finally, we propose a mechanism to dynamically coalesce services on commonly called paths into a single container and demonstrate a further 7.5% improvement in throughput. | DL48: Microservices; Performance; Container-scheduling; NUMA
A49: PL5RVD52 | B49: conferencePaper | C49: 2019 | D49: Sriraman, Akshitha; Dhanotia, Abhishek; Wenisch, Thomas F. | E49: SoftSKU: optimizing server architectures for microservice diversity @scale | F49: Proceedings of the 46th International Symposium on Computer Architecture | G49: 978-1-4503-6669-4 | I49: 10.1145/3307650.3322227 | J49: https://doi.org/10.1145/3307650.3322227 | K49: 2019 | L49: 45734.379 | M49: 45734.379 | O49: 513‚Äì526 | V49: ISCA '19 | Z49: Association for Computing Machinery | AA49: New York, NY, USA | AI49: event-place: Phoenix, Arizona | CL49: The variety and complexity of microservices in warehouse-scale data centers has grown precipitously over the last few years to support a growing user base and an evolving product portfolio. Despite accelerating microservice diversity, there is a strong requirement to limit diversity in underlying server hardware to maintain hardware resource fungibility, preserve procurement economies of scale, and curb qualification/test overheads. As such, there is an urgent need for strategies that enable limited server CPU architectures (a.k.a "SKUs") to provide performance and energy efficiency over diverse microservices. To this end, we first undertake a comprehensive characterization of the top seven microservices that run on the compute-optimized data center fleet at Facebook.Our characterization reveals profound diversity in OS and I/O interaction, cache misses, memory bandwidth utilization, instruction mix, and CPU stall behavior. Whereas customizing a CPU SKU for each microservice might be beneficial, it is prohibitive. Instead, we argue for "soft SKUs", wherein we exploit coarse-grain (e.g., boot time) configuration knobs to tune the platform for a particular microservice. We develop a tool, ŒºSKU, that automates search over a soft-SKU design space using A/B testing in production and demonstrate how it can obtain statistically significant gains (up to 7.2% and 4.5% performance improvement over stock and production servers, respectively) with no additional hardware requirements. | DL49: microservice; resource fungibility; soft SKU
A50: 4TGPKCVJ | B50: conferencePaper | C50: 2023 | D50: Antoniou, Georgia; Volos, Haris; Bartolini, Davide B.; Rollet, Tom; Sazeides, Yiannakis; Yahya, Jawad Haj | E50: AgilePkgC: An Agile System Idle State Architecture for Energy Proportional Datacenter Servers | F50: Proceedings of the 55th Annual IEEE/ACM International Symposium on Microarchitecture | G50: 978-1-6654-6272-3 | I50: 10.1109/MICRO56248.2022.00065 | J50: https://doi.org/10.1109/MICRO56248.2022.00065 | K50: 2023 | L50: 45734.379 | M50: 45734.379 | O50: 851‚Äì867 | V50: MICRO '22 | Z50: IEEE Press | AA50: Chicago, Illinois, USA | CL50: Modern user-facing applications deployed in data-centers use a distributed system architecture that exacerbates the latency requirements of their constituent microservices (30‚Äì250Œºs). Existing CPU power-saving techniques degrade the performance of these applications due to the long transition latency (order of 100Œºs) to wake up from a deep CPU idle state (C-state). For this reason, server vendors recommend only enabling shallow core C-states (e.g., CC1) for idle CPU cores, thus preventing the system from entering deep package C-states (e.g., PC6) when all CPU cores are idle. This choice, however, impairs server energy proportionality since power-hungry resources (e.g., IOs, uncore, DRAM) remain active even when there is no active core to use them. As we show, it is common for all cores to be idle due to the low average utilization (e.g., 5 ‚Äì 20%) of datacenter servers running user-facing applications.We propose to reap this opportunity with AgilePkgC (APC), a new package C-state architecture that improves the energy proportionality of server processors running latency-critical applications. APC implements PC1A (package C1 agile), a new deep package C-state that a system can enter once all cores are in a shallow C-state (i.e., CC1) and has a nanosecond-scale transition latency. PC1A is based on four key techniques. First, a hardware-based agile power management unit (APMU) rapidly detects when all cores enter a shallow core C-state (CC1) and triggers the system-level power savings control flow. Second, an IO Standby Mode (IOSM) places IO interfaces (e.g., PCIe, DMI, UPI, DRAM) in shallow (nanosecond-scale transition latency) low-power modes. Third, a CLM Retention (CLMR) mode rapidly reduces the CLM (Cache-and-home-agent, Last-level-cache, and Mesh network-on-chip) domain's voltage to its retention level, drastically reducing its power consumption. Fourth, APC keeps all system PLLs active in PC1A to allow nanosecond-scale exit latency by avoiding PLL re-locking overhead.Combining these techniques enables significant power savings while requiring less than 200ns transition latency, &gt;250√ó faster than existing deep package C-states (e.g., PC6), making PC1A practical for datacenter servers. Our evaluation based on an Intel Skylake-based server shows that APC reduces the energy consumption of Memcached by up to 41% (25% on average) with &lt;0.1% performance degradation. APC provides similar benefits for other representative workloads.
A51: QIFREQCE | B51: conferencePaper | C51: 2024 | D51: Holzer, Stefan; Frangoudis, Pantelis; Tsigkanos, Christos; Dustdar, Schahram | E51: SMT-as-a-Service for Fog-Supported Cyber-Physical Systems | F51: Proceedings of the 25th International Conference on Distributed Computing and Networking | G51: 979-8-4007-1673-7 | I51: 10.1145/3631461.3631562 | J51: https://doi.org/10.1145/3631461.3631562 | K51: 2024 | L51: 45734.379 | M51: 45734.379 | O51: 154‚Äì163 | V51: ICDCN '24 | Z51: Association for Computing Machinery | AA51: New York, NY, USA | AI51: event-place: Chennai, India | CL51: Various properties related with the safe, correct, and efficient operation of Cyber-Physical Systems (CPS) can be expressed via formal languages and checked at runtime or offline by appropriate verification tools. Such tools operate on monitoring data about the CPS state and functionality, typically collected from IoT devices. A specific approach involves modeling CPS state or operations using Satisfiability Modulo Theories (SMT) formalisms, and using solver software to check whether given CPS properties are satisfied or to derive satisfiable CPS configurations. The computational requirements of this process can however be significant, which challenges its timely execution on IoT/edge devices where input date originate. To address this challenge, we present an architecture that allows the distributed execution of SMT problem solving workloads over the computing continuum as a service. Our design supports arbitrary hierarchies of solver nodes running anywhere from the IoT device to the cloud, each independently executing decision-making logic as to whether to solve an SMT problem instance locally or to recursively offload the task to other nodes in the continuum. We demonstrate the benefits of offloading by implementing and quantitatively evaluating different reinforcement learning-based decision-making strategies addressing latency minimization and energy efficiency goals, and showcase the practicability of our scheme in a fog robotics proof-of-concept. | DL51: IoT; Computing continuum; Computation Offloading; Fog Robotics; Satisfiability Modulo Theories
A52: 6R6TSUSW | B52: conferencePaper | C52: 2022 | D52: Tootaghaj, Diman Zad; Mercian, Anu; Adarsh, Vivek; Sharifian, Mehrnaz; Sharma, Puneet | E52: SmartNICs at edge for transient compute elasticity | F52: Proceedings of the 3rd International Workshop on Distributed Machine Learning | G52: 978-1-4503-9922-7 | I52: 10.1145/3565010.3569065 | J52: https://doi.org/10.1145/3565010.3569065 | K52: 2022 | L52: 45734.379 | M52: 45734.379 | O52: 9‚Äì15 | V52: DistributedML '22 | Z52: Association for Computing Machinery | AA52: New York, NY, USA | AI52: event-place: Rome, Italy | CL52: This paper proposes a new architecture that strategically harvests the untapped compute capacity of the SmartNICs to offload transient microservices workload spikes, thereby reducing the SLA violations while providing better performance/energy consumption. This is particularly important for ML workloads at Edge deployments with stringent SLA requirements. Usage of the untapped compute capacity is more favorable than deploying extra servers, as SmartNICs are economically and operationally more desirable. We propose Spike-Offload, a low-cost and scalable platform that leverages machine learning to predict the spikes and orchestrates seamless offloading of generic microservices workloads to the SmartNICs, eliminating the need for pre-deploying expensive host servers and their under-utilization. Our SpikeOffload evaluation shows that SLA violations can be reduced by up to 20% for specific workloads. Furthermore, we demonstrate that for specific workloads our approach can potentially reduce capital expenditure (CAPEX) by more than 40%. Also, performance per unit energy consumption can be improved by upto 2X. | DL52: edge; serverless computing; application offload; SmartNIC
A53: 3M6P9IQX | B53: conferencePaper | C53: 2023 | D53: Grafenhorst, Simon; F√∂rderer, Kevin; Hagenmeyer, Veit | E53: Distribution Grid Monitoring Based on&nbsp;Widely Available Smart Plugs | F53: Energy Informatics: Third Energy Informatics Academy Conference, EI.A 2023, Campinas, Brazil, December 6‚Äì8, 2023, Proceedings, Part II | G53: 978-3-031-48651-7 | I53: 10.1007/978-3-031-48652-4_13 | J53: https://doi.org/10.1007/978-3-031-48652-4_13 | K53: 2023 | L53: 45734.379 | M53: 45734.379 | O53: 195‚Äì212 | Z53: Springer-Verlag | AA53: Berlin, Heidelberg | AI53: event-place: Campinas, Brazil | CL53: The growing popularity of e-mobility, heat pumps, and renewable generation such as photovoltaics is leading to scenarios which the distribution grid was not originally designed for. Moreover, parts of the distribution grid are only sparsely instrumented, leaving the distribution system operator unaware of possible bottlenecks resulting from the introduction of such loads and renewable generation. To overcome this lack of information, we propose the use of widely available smart home devices, such as smart plugs, for grid monitoring. We detail the aggregation and storage of smart plug measurements for distribution grid monitoring and examine the accuracy of the measurements. A case study shows how the average monitoring error in a distribution grid area decreases the more measurement devices are installed. Hence, simple smart plugs can help with distribution grid monitoring and provide valuable information to the DSO. | DL53: Distribution Grid Monitoring; Smart Grid; Smart Home Measurement Device
A54: GRL4PFL6 | B54: conferencePaper | C54: 2024 | D54: Daniel, Jo√£o; Wang, Xiaofeng; Guerra, Eduardo | E54: Pattern Language for Leveraging Metadata to Reusability in APIs | F54: Proceedings of the 29th European Conference on Pattern Languages of Programs, People, and Practices | G54: 979-8-4007-1683-6 | I54: 10.1145/3698322.3698344 | J54: https://doi.org/10.1145/3698322.3698344 | K54: 2024 | L54: 45734.379 | M54: 45734.379 | V54: EuroPLoP '24 | Z54: Association for Computing Machinery | AA54: New York, NY, USA | CL54: Nowadays, corporate systems are heterogeneous, with distributed pieces that collaborate to fulfill the requirements. Communication between autonomous components becomes a key aspect to maintain the quality of the architecture. As a consequence, remote APIs are in focus: the quality in their design might significantly impact the quality of the interacting components. We aim to assist practitioners with designing reusable APIs. We present 8 patterns: (i) ‚ÄúFlexibilize the Ingestion‚Äù that structures an API to provide seamless integration by accepting heterogeneous structures as input; (ii) ‚ÄúEnrich with Metadata‚Äù that adds a new layer containing metadata to the messages exchanged; (iii) ‚ÄúAgree on Meta Structure‚Äù that defines a common metadata structure among the communicating parts; (iv) ‚ÄúPlug the Processors In‚Äù that proposes decoupled but composable handlers for the data and metadata; then (v) ‚ÄúEmbed Metadata‚Äù, (vi) ‚ÄúConfigure Meta in Runtime‚Äù and (vii) ‚ÄúConfigure Meta during Deploy‚Äù propose different settings for the placement and setting of metadata; and (viii) ‚ÄúAdapt the Ingestion‚Äù that includes an adapter dedicated to set the metadata for ingestion when it is impossible to change the original sender. | DL54: API; Metadata; Reusability
A55: 9Y7CTWN2 | B55: conferencePaper | C55: 2021 | D55: Tzenetopoulos, Achilleas; Marantos, Charalampos; Gavrielides, Giannos; Xydis, Sotirios; Soudris, Dimitrios | E55: FADE: FaaS-inspired application decomposition and Energy-aware function placement on the Edge | F55: Proceedings of the 24th International Workshop on Software and Compilers for Embedded Systems | G55: 978-1-4503-9166-5 | I55: 10.1145/3493229.3493306 | J55: https://doi.org/10.1145/3493229.3493306 | K55: 2021 | L55: 45734.379 | M55: 45734.379 | O55: 7‚Äì10 | V55: SCOPES '21 | Z55: Association for Computing Machinery | AA55: New York, NY, USA | AI55: event-place: Eindhoven, Netherlands | CL55: Lately, more and more applications are deployed on heterogeneous, power-constrained edge-computing devices. Bringing computation closer to the data, contributes both to latency and energy consumption reduction due to the elimination of excessive data transfers. However, while the main concern in such environments is the minimization of energy consumption, the heterogeneity in compute resources found at the edge may lead to Quality of Service (QoS) violations. At the same time, Serverless computing, the next frontier of Cloud computing has emerged to offer unprecedented elasticity by utilizing fine-grained, stateless functions. The reduction in the execution time and the modest memory footprint of such decomposed applications, allow for fine-grained resource multiplexing. In this work, we propose a methodology for application decomposition into fine-grained functions and energy-aware function placement on a cluster of edge devices subject to user-specified QoS guarantees. | DL55: resource management; serverless; energy-aware
A56: HWYSISBN | B56: conferencePaper | C56: 2024 | D56: Fu, Silvery D.; Zhang, Hong; Teoh, Ryan; Priadka, Taras; Ratnasamy, Sylvia | E56: Toward Data-Centric Service Composition | F56: Proceedings of the 23rd ACM Workshop on Hot Topics in Networks | G56: 979-8-4007-1272-2 | I56: 10.1145/3696348.3702013 | J56: https://doi.org/10.1145/3696348.3702013 | K56: 2024 | L56: 45734.379 | M56: 45734.379 | O56: 360‚Äì367 | V56: HotNets '24 | Z56: Association for Computing Machinery | AA56: New York, NY, USA | AI56: event-place: Irvine, CA, USA | CL56: Microservices are increasingly used in modern applications, leading to a growing need for effective service composition solutions. However, we argue that traditional API-centric composition mechanisms (e.g., RPC, REST, and Pub/Sub) hamper the modularity of microservices. These mechanisms introduce rigid code-level coupling, scatter composition logic, and hinder visibility into cross-service data exchanges. Ultimately, these limitations complicate the maintenance and evolution of microservice-based applications. In this paper, we propose a rethinking of service composition and present Knactor, a new data-centric composition framework to restore the modularity that microservices were intended to offer. Knactor decouples service composition from service development, allowing composition to be implemented as explicit data exchanges among multiple services. Our initial case study suggests that this approach not only simplifies service composition but also opens up opportunities for data-driven policies and optimizations. | DL56: Microservices; Design Principles; Service Composition
A57: 43GWV8LF | B57: conferencePaper | C57: 2019 | D57: Dobaj, J√ºrgen; Schuss, Markus; Krisper, Michael; Boano, Carlo Alberto; Macher, Georg | E57: Dependable mesh networking patterns | F57: Proceedings of the 24th European Conference on Pattern Languages of Programs | G57: 978-1-4503-6206-1 | I57: 10.1145/3361149.3361174 | J57: https://doi.org/10.1145/3361149.3361174 | K57: 2019 | L57: 45734.379 | M57: 45734.379 | V57: EuroPLop '19 | Z57: Association for Computing Machinery | AA57: New York, NY, USA | AI57: event-place: Irsee, Germany | CL57: In our daily life, we are increasingly relying on connected systems ranging from smart health care devices to industrial and intelligent transportation systems, as well as smart homes and cities. The unavailability or malfunctioning of these systems could threaten human life, cause environmental damage, and significant financial loss. To prevent such large scale and mission-critical systems from malfunctioning, it is of utmost importance to establish and guaranty reliable connections to attain a dependable networked system. Generally, mesh networking technologies are used for building such systems since mesh networks provide the best performance characteristics regarding fault-tolerance, throughput, resource usage, and service level flexibility.In this paper, we summarize the major challenges in dependable network design, to subsequently present three patterns that approach redundancy on the hardware level, software-defined networking, and cross-cutting concerns like monitoring and service discovery within distributed networked systems. These three patterns should help designers and engineers in choosing the appropriate technologies for building dependable networked systems at all scales. Since dependable network engineering requires a holistic system-wide design and engineering approach, we also present a pattern map guiding to complementary and closely related patterns. System architects and system engineers responsible for building mixed-criticality systems, internet-of-things (IoT), and industrial Internet-of-Things (IIoT) systems are the target audience of the patterns presented in this paper. | DL57: microservices; cloud architecture; dependability; IaaS; IIoT; industry 4.0; infrastructure-as-a-service; IoT; logical mesh pattern; network architecture; network design; physical mesh pattern; service mesh pattern; service-oriented architecture; SoA
A58: TZQAMCSP | B58: conferencePaper | C58: 2020 | D58: Caporuscio, Mauro; D‚ÄôAngelo, Mirko; Grassi, Vincenzo; Mirandola, Raffaela | E58: Decentralized Architecture for Energy-Aware Service Assembly | F58: Software Architecture: 14th European Conference, ECSA 2020, L'Aquila, Italy, September 14‚Äì18, 2020, Proceedings | G58: 978-3-030-58922-6 | I58: 10.1007/978-3-030-58923-3_4 | J58: https://doi.org/10.1007/978-3-030-58923-3_4 | K58: 2020 | L58: 45734.379 | M58: 45734.379 | O58: 57‚Äì72 | Z58: Springer-Verlag | AA58: Berlin, Heidelberg | AI58: event-place: L'Aquila, Italy | CL58: Contemporary application domains make more and more appealing the vision of applications built as a dynamic and opportunistic assembly of autonomous and independent resources. However, the adoption of such paradigm is challenged by: (i) the openness and scalability needs of the operating environment, which rule out approaches based on centralized architectures and, (ii) the increasing concern for sustainability issues, which makes particularly relevant, in addition to QoS constraints, the goal of reducing the application energy footprint. In this context, we contribute by proposing a decentralized architecture to build a fully functional assembly of distributed services, able to optimize its energy consumption, paying also attention to issues concerning the delivered quality of service. We suggest suitable indexes to measure from different perspectives the energy efficiency of the resulting assembly, and present the results of extensive simulation experiments to assess the effectiveness of our approach.
A59: NTXLFUFC | B59: conferencePaper | C59: 2024 | D59: Wang, Botao; Xu, Xu; Zhuo, Lin; Yuan, Xiangyu; Wang, Longzhi; Sun, Qixing; Fu, Wei; Teng, Kah Hou | E59: A Method for Optimizing Elastic Scaling Resources of Private Cloud in Digital Grid | F59: Proceedings of the 2024 9th International Conference on Cyber Security and Information Engineering | G59: 979-8-4007-1813-7 | I59: 10.1145/3689236.3696171 | J59: https://doi.org/10.1145/3689236.3696171 | K59: 2024 | L59: 45734.379 | M59: 45734.379 | O59: 944‚Äì951 | V59: ICCSIE '24 | Z59: Association for Computing Machinery | AA59: New York, NY, USA | CL59: Cloud computing improves server utilization and reduces the number of physical servers through virtualization technology, which directly reduces energy consumption and corresponding carbon emissions. The elastic scalability of cloud platforms allows resources to automatically expand or reduce according to actual needs, avoiding excessive resource allocation and waste. In order to further investigate the positive effects of cloud platform elastic scaling on resources in enterprise IT management. This paper summarizes the change rules of elastic scaling resources on cloud in large enterprises by sorting out the business operation characteristics and resource change rules, and classifies and analyzes the three demand scenarios of periodic changes, jitter changes, and stable changes of business resources. It proves through experimental methods that the containerized deployment and elastic scaling configuration methods of cloud platforms can effectively improve the operation efficiency of cloud resources. The application method has also been promoted and verified in many different regions across the country, further proving that it can effectively help enterprises improve resource efficiency and reduce operating costs, and provide a reference for large-scale application of elastic scaling configuration in large enterprises. | DL59: Kubernetes; Cloud platform; Digital grid; Elastic scaling; Resource scheduling
A60: K4WHX267 | B60: conferencePaper | C60: 2024 | D60: Maranh√£o, Jo√£o Jos√©; Guerra, Eduardo Martins | E60: A Prompt Pattern Sequence Approach to Apply Generative AI in Assisting Software Architecture Decision-making | F60: Proceedings of the 29th European Conference on Pattern Languages of Programs, People, and Practices | G60: 979-8-4007-1683-6 | I60: 10.1145/3698322.3698324 | J60: https://doi.org/10.1145/3698322.3698324 | K60: 2024 | L60: 45734.379 | M60: 45734.379 | V60: EuroPLoP '24 | Z60: Association for Computing Machinery | AA60: New York, NY, USA | CL60: This paper proposes an approach that employs generative AI, specifically GPT models, to enhance decision-making in software architecture through a sequence of prompt patterns. Five prompt patterns are introduced, each targeting software architects‚Äô specific challenges when navigating complex design decisions. Through a structured and context-aware decision flow, we demonstrate how these patterns can mitigate risks, manage uncertainties, and optimize functional and non-functional requirements. The proposed approach is evaluated in two real-world scenarios and one fictional case, illustrating its practical application in optimizing operations and ensuring scalability, security, and performance. While AI demonstrates transformative potential in aiding architectural practices, we also highlight its limitations, emphasizing the importance of human oversight in validating technical assumptions and avoiding over-reliance on automated tools. This paper contributes to the ongoing dialogue on how AI can be integrated into software architecture to foster more efficient, informed, and context-sensitive decision-making processes for architects. | DL60: Artificial Intelligence; AI Generative; Architecture Decision-Making; Design Patterns; Prompt Engineering; Prompt Patterns Sequence; Software Architecture
A61: 3MWFAVFG | B61: conferencePaper | C61: 2020 | D61: Zimmermann, Olaf; L√ºbke, Daniel; Zdun, Uwe; Pautasso, Cesare; Stocker, Mirko | E61: Interface Responsibility Patterns: Processing Resources and Operation Responsibilities | F61: Proceedings of the European Conference on Pattern Languages of Programs 2020 | G61: 978-1-4503-7769-0 | I61: 10.1145/3424771.3424822 | J61: https://doi.org/10.1145/3424771.3424822 | K61: 2020 | L61: 45734.379 | M61: 45734.379 | V61: EuroPLoP '20 | Z61: Association for Computing Machinery | AA61: New York, NY, USA | AI61: event-place: Virtual Event, Germany | CL61: Remote Application Programming Interfaces (APIs), as for instance offered in microservices architectures, are used in almost any distributed system today and are thus enablers for many digitalization efforts. It is hard to design such APIs so that they are easy and effective to use; maintaining their runtime qualities while preserving backward compatibility is equally challenging. Finding well suited granularities in terms of the architectural capabilities of endpoints and the read-write semantics of their operations are particularly important design concerns. Existing pattern languages have dealt with local APIs in object-oriented programming, with remote objects, with queue-based messaging and with service-oriented computing platforms. However, patterns or equivalent guidances for the architectural design of API endpoints, operations and their request and response message structures are still missing. In this paper, we extend our microservice API pattern language (MAP) and introduce endpoint role and operation responsibility patterns, namely Processing Resource, Computation Function, State Creation Operation, Retrieval Operation, and State Transition Operation. Known uses and examples of the patterns are drawn from public Web APIs, as well as application development and system integration projects the authors have been involved in.
A62: JBUZIVQT | B62: conferencePaper | C62: 2025 | D62: Akmal, Muhammad Uzair; Asif, Saara; Koval, Leonid; Mathias, Selvine G.; Knollmeyer, Simon; Grossmann, Daniel | E62: Layered Data-Centric AI to&nbsp;Streamline Data Quality Practices for&nbsp;Enhanced Automation | F62: Artificial Intelligence: Methodology, Systems, and Applications: 19th International Conference, AIMSA 2024, Varna, Bulgaria, September 18‚Äì20, 2024, Proceedings | G62: 978-3-031-81541-6 | I62: 10.1007/978-3-031-81542-3_11 | J62: https://doi.org/10.1007/978-3-031-81542-3_11 | K62: 2025 | L62: 45734.379 | M62: 45734.379 | O62: 128‚Äì142 | Z62: Springer-Verlag | AA62: Berlin, Heidelberg | AI62: event-place: Varna, Bulgaria | CL62: Most artificial intelligence (AI) applications are designed under the model-centric AI (MCAI) approach, where data scientists aim to optimize the machine learning (ML) models starting with fixed, preprocessed data. However, businesses often struggle with limited datasets, changes in data over time, and limited ML knowledge, making it difficult to maintain data quality. One potential approach is data-centric AI (DCAI), which systematically improves the data quality used to build AI systems. However, rapid growth in data volume leads to challenges in selecting the most suitable operations for enhancing data quality thereby maintaining data accuracy, completeness, consistency, and reliability in real-world applications. To address this gap, we propose a novel framework, namely Layered Data-Centric AI (LDCAI) by expanding upon the existing DCAI Pipeline. LDCAI employs a three-layered approach, starting with the DCAI layer which generates the initial training data. This data is then analyzed and refined in the Data Analysis (DA) layer by a team of data scientists and domain experts. The refined data is later sent to the Data Quality Control (DQC) layer for additional quality checks and improvements by data scientists. The entire process can be iterated as needed to continuously improve data quality, which can be fed back into the DCAI layer‚Äôs model to achieve better predictions and outcomes. The implementation is illustrated through a scalable and customizable architecture designed for optimizing data quality within AI systems. | DL62: Artificial intelligence; Data analysis; Data quality; Data-centric
A63: EYMNN88U | B63: conferencePaper | C63: 2019 | D63: Huber, Florian; K√∂rber, Nikolai; Mock, Markus | E63: Selena: a Serverless Energy Management System | F63: Proceedings of the 5th International Workshop on Serverless Computing | G63: 978-1-4503-7038-7 | I63: 10.1145/3366623.3368134 | J63: https://doi.org/10.1145/3366623.3368134 | K63: 2019 | L63: 45734.379 | M63: 45734.379 | O63: 7‚Äì12 | V63: WOSC '19 | Z63: Association for Computing Machinery | AA63: New York, NY, USA | AI63: event-place: Davis, CA, USA | CL63: Reduction of CO2 emissions has become a significant challenge faced by humanity today. Energy management systems try to contribute to addressing this challenge by enabling an intelligent use and combination of different energy sources by capturing and visualizing energy usage and production data to enable energy efficiency improvement measures. In this paper, we present Selena, a prototypical energy management system that is implemented using the serverless computing paradigm. Essential design goals for Selena are both extensibility, so that many different data sources and providers (e.g., measurement systems) can be integrated easily, as well as efficient scalability, so that the system can be used from small (e.g., one building) to large installations (potentially entire neighborhoods) with deployment cost commensurate with the installation size. Our initial experiences with Selena indicate that the serverless paradigm is very well suited to capture and process energy-related data reliably and has excellent scaling properties due to the elastic compute platform that it is built upon. | DL63: microservices; IoT; AWS Lambda; energy management systems; FaaS; serverless computing
A64: J7PIFZQW | B64: conferencePaper | C64: 2019 | D64: Kaur, Kuljeet; Garg, Sahil; Kaddoum, Georges; Ahmed, Syed Hassan; Jayakody, Dushantha Nalin K. | E64: En-OsCo: Energy-aware Osmotic Computing Framework using Hyper-heuristics | F64: Proceedings of the ACM MobiHoc Workshop on Pervasive Systems in the IoT Era | G64: 978-1-4503-6805-6 | I64: 10.1145/3331052.3332473 | J64: https://doi.org/10.1145/3331052.3332473 | K64: 2019 | L64: 45734.379 | M64: 45734.379 | O64: 19‚Äì24 | V64: PERSIST-IoT '19 | Z64: Association for Computing Machinery | AA64: New York, NY, USA | AI64: event-place: Catania, Italy | CL64: The proliferation of the Internet of Things (IoT) has paved the way for many cloud based applications such as smart grid, healthcare, traffic management, finance, etc. In this vein, the need of transferring large data-streams to remote data centers is a key concern for modern Cloud-based IoT paradigms. This disrupts the remote Cloud Computing model, moving applications, data and computing resources to the logical extremes of the network. Thus, to handle streaming data in IoT environments, an efficient IoT-based computing model that can dynamically handle the interplay between Cloud and Edge data centers is required. In this direction, a recent paradigm, popularly known as Osmotic Computing, has emerged to ensure the acceptable performance of widely dispersed services. However, the burden of data-offloading across multiple data centers usually leads to a consequent increase in their energy consumption which in-turn will affect the overall Quality of Service (QoS) of the IoT-based applications. Keeping focus on all these issues, a consolidated decision making framework for Osmotic Computing, i.e., En-OsCo, is designed to ensure the energy-aware dynamic management of resources. The proposed framework incorporates four significant contributions: i) Resource monitoring of Edge data centers using Extended Kalman Filter, ii) Optimal dispatch of incoming services to the Edge/Cloud setup using Hyper-heuristics, iii) Minimizing the energy consumption of underlying data centers and reducing the service latency, and iv) Reducing the search space of Hyper-heuristics by keeping track of previously made decisions using Universal Streaming Monitoring. Further, in order to validate the efficacy of the proposed En-OsCo framework, ContainerCloudSim has been used in combination of HyFlex on PlanetLab datasets. The obtained results validate the purpose of the proposed scheme in minimizing the overall energy consumption of the computing setup while considerably reducing the latency. | DL64: Cloud Computing; Edge Computing; and Osmotic Computing; Energy Minimization; Extended Kalman Filter; Hyper-heuristics; Latency Minimization
A65: TYZQHQBX | B65: conferencePaper | C65: 2018 | D65: Li, Fei; Gelbke, Lars | E65: Microservice architecture in industrial software delivery on edge devices | F65: Proceedings of the 19th International Conference on Agile Software Development: Companion | G65: 978-1-4503-6422-5 | I65: 10.1145/3234152.3234196 | J65: https://doi.org/10.1145/3234152.3234196 | K65: 2018 | L65: 45734.379 | M65: 45734.379 | V65: XP '18 | Z65: Association for Computing Machinery | AA65: New York, NY, USA | AI65: event-place: Porto, Portugal | CL65: Production in Industry 4.0 calls for flexible configurations, customizable features, frequent changes, and above all, short time to market, which poses significant challenges to the practices of industrial software development and delivery. However, under strict regulations and non-negotiable requirements on safety, reliability and compliance, industrial software is still dominated by monolithic architecture that usually requires planned downtime and manual installation for each update. The result is a typical release cycle of 12-18 months with several patches during the release cycle.This paper reports our experiences in applying microservice architecture, and delivery pipeline to achieve continuous deployment for industrial control software on edge devices. They are characterized by their physical proximity to industrial equipment, limited computational resources, high avail-ability, and highly heterogeneous software environments in order to accommodate various industrial protocols and processes. | DL65: microservice; edge computing; industrial software
A66: VRST2P3J | B66: conferencePaper | C66: 2023 | D66: Buschmann, Philippe; Shorim, Mostafa H. M.; Helm, Max; Br√∂ring, Arne; Carle, Georg | E66: Task Allocation in Industrial Edge Networks with Particle Swarm Optimization and Deep Reinforcement Learning | F66: Proceedings of the 12th International Conference on the Internet of Things | G66: 978-1-4503-9665-3 | I66: 10.1145/3567445.3571114 | J66: https://doi.org/10.1145/3567445.3571114 | K66: 2023 | L66: 45734.379 | M66: 45734.379 | O66: 239‚Äì247 | V66: IoT '22 | Z66: Association for Computing Machinery | AA66: New York, NY, USA | AI66: event-place: Delft, Netherlands | CL66: To avoid the disadvantages of a cloud-centric infrastructure, next-generation industrial scenarios focus on using distributed edge networks. Task allocation in distributed edge networks with regards to minimizing the energy consumption is NP-hard and requires considerable computational effort to obtain optimal results with conventional algorithms like Integer Linear Programming (ILP). We extend an existing ILP problem including an ILP heuristic for multi-workflow allocation and propose a Particle Swarm Optimization (PSO) and a Deep Reinforcement Learning (DRL) algorithm. PSO and DRL outperform the ILP heuristic with a median optimality gap of and against . DRL has the lowest upper bound for the optimality gap. It performs better than PSO for problem sizes of more than 25 tasks and PSO fails to find a feasible solution for more than 60 tasks. The execution time of DRL is significantly faster with a maximum of 1 s in comparison to PSO with a maximum of 361 s. In conclusion, our experiments indicate that PSO is more suitable for smaller and DRL for larger sized task allocation problems. | DL66: Internet of Things (IoT); Edge Computing; Deep Reinforcement Learning; Integer Linear Programming; Particle Swarm Optimization; Task Allocation
A67: FHN5QKFQ | B67: conferencePaper | C67: 2024 | D67: Farahani, Reza; Loh, Frank; Roman, Dumitru; Prodan, Radu | E67: Serverless Workflow Management on the Computing Continuum: A Mini-Survey | F67: Companion of the 15th ACM/SPEC International Conference on Performance Engineering | G67: 979-8-4007-0445-1 | I67: 10.1145/3629527.3652901 | J67: https://doi.org/10.1145/3629527.3652901 | K67: 2024 | L67: 45734.379 | M67: 45734.379 | O67: 146‚Äì150 | V67: ICPE '24 Companion | Z67: Association for Computing Machinery | AA67: New York, NY, USA | AI67: event-place: London, United Kingdom | CL67: The growing desire among application providers for a cost model based on pay-per-use, combined with the need for a seamlessly integrated platform to manage the complex workflows of their applications, has spurred the emergence of a promising computing paradigm known as serverless computing. Although serverless computing was initially considered for cloud environments, it has recently been extended to other layers of the computing continuum, i.e., edge and fog. This extension emphasizes that the proximity of computational resources to data sources can further reduce costs and improve performance and energy efficiency. However, orchestrating the computing continuum in complex application workflows, including a set of serverless functions, introduces new challenges. This paper investigates the opportunities and challenges introduced by serverless computing for workflow management systems (WMS) on the computing continuum. In addition, the paper provides a taxonomy of state-of-the-art WMSs and reviews their capabilities. | DL67: serverless computing; edge-cloud continuum; function scheduling; function-as-a-service (faas); service orchestration; sustainability; workflow; workflow management systems (wms)
A68: B9RSNMLF | B68: conferencePaper | C68: 2017 | D68: Martins, Lucas M. C. e; Filho, Francisco L. de Caldas; J√∫nior, Rafael T. de Sousa; Giozza, William F.; da Costa, Jo√£o Paulo C.L. | E68: Increasing the Dependability of IoT Middleware with Cloud Computing and Microservices | F68: Companion Proceedings of The10th International Conference on Utility and Cloud Computing | G68: 978-1-4503-5195-9 | I68: 10.1145/3147234.3148092 | J68: https://doi.org/10.1145/3147234.3148092 | K68: 2017 | L68: 45734.379 | M68: 45734.379 | O68: 203‚Äì208 | V68: UCC '17 Companion | Z68: Association for Computing Machinery | AA68: New York, NY, USA | AI68: event-place: Austin, Texas, USA | CL68: Internet of Things (IoT) has left the experimental field and is reaching the final consumer in areas such as residential automation, health, transportation and government support. Since these are applications intrinsically linked to the physical world, they require more attention in aspects related to their dependability. Focusing on its availability and reliability, we present a proposal to apply the Microservices architectural pattern in an IoT middleware with web services in the monolithic architecture. We describe the reengineering that must be done in this middleware and, finally, we analyze the advantages and disadvantages of this approach, highlighting the availability improvement, optimization of the infrastructure resources, the ease of maintenance and evolution, as well as the inclination to the elasticity that the architecture allows. | DL68: cloud computing; microservices; dependability; internet of things (iot); middleware; soa.
A69: VMMJJNTA | B69: conferencePaper | C69: 2023 | D69: Zhu, Xiangfeng; She, Guozhen; Xue, Bowen; Zhang, Yu; Zhang, Yongsu; Zou, Xuan Kelvin; Duan, XiongChun; He, Peng; Krishnamurthy, Arvind; Lentz, Matthew; Zhuo, Danyang; Mahajan, Ratul | E69: Dissecting Overheads of Service Mesh Sidecars | F69: Proceedings of the 2023 ACM Symposium on Cloud Computing | G69: 979-8-4007-0387-4 | I69: 10.1145/3620678.3624652 | J69: https://doi.org/10.1145/3620678.3624652 | K69: 2023 | L69: 45734.379 | M69: 45734.379 | O69: 142‚Äì157 | V69: SoCC '23 | Z69: Association for Computing Machinery | AA69: New York, NY, USA | AI69: event-place: Santa Cruz, CA, USA | CL69: Service meshes play a central role in the modern application ecosystem by providing an easy and flexible way to connect microservices of a distributed application. However, because of how they interpose on application traffic, they can substantially increase application latency and its resource consumption. We develop a tool called MeshInsight to help developers quantify the overhead of service meshes in deployment scenarios of interest and make informed trade-offs about their functionality vs. overhead. Using MeshInsight, we confirm that service meshes can have high overhead‚Äîup to 269% higher latency and up to 163% more virtual CPU cores for our benchmark applications‚Äîbut the severity is intimately tied to how they are configured and the application workload. IPC (inter-process communication) and socket writes dominate when the service mesh operates as a TCP proxy, but protocol parsing dominates when it operates as an HTTP proxy. MeshInsight also enables us to study the end-to-end impact of optimizations to service meshes. We show that not all seemingly-promising optimizations lead to a notable overhead reduction in realistic settings. | DL69: Cloud computing; Microservices; Service Mesh
A70: 6LTQZQ7H | B70: conferencePaper | C70: 2018 | D70: Tesfatsion, Selome Kostentinos; Klein, Cristian; Tordsson, Johan | E70: Virtualization Techniques Compared: Performance, Resource, and Power Usage Overheads in Clouds | F70: Proceedings of the 2018 ACM/SPEC International Conference on Performance Engineering | G70: 978-1-4503-5095-2 | I70: 10.1145/3184407.3184414 | J70: https://doi.org/10.1145/3184407.3184414 | K70: 2018 | L70: 45734.379 | M70: 45734.379 | O70: 145‚Äì156 | V70: ICPE '18 | Z70: Association for Computing Machinery | AA70: New York, NY, USA | AI70: event-place: Berlin, Germany | CL70: Virtualization solutions based on hypervisors or containers are enabling technologies for scalable, flexible, and cost-effective resource sharing. As the fundamental limitations of each technology are yet to be understood, they need to be regularly reevaluated to better understand the trade-off provided by latest technological advances. This paper presents an in-depth quantitative analysis of virtualization overheads in these two groups of systems and their gaps relative to native environments based on a diverse set of workloads that stress CPU, memory, storage, and networking resources. KVM and XEN are used to represent hypervisor-based virtualization, and LXC and Docker for container-based platforms. The systems were evaluated with respect to several cloud resource management dimensions including performance, isolation, resource usage, energy efficiency, start-up time, and density. Our study is useful both to practitioners to understand the current state of the technology in order to make the right decision in the selection, operation and/or design of platforms and to scholars to illustrate how these technologies evolved over time. | DL70: performance; containers; power; isolation; resource usage; virtualization overhead; VMS
A71: JPE2GTE8 | B71: conferencePaper | C71: 2018 | D71: Sampedro, Zebula; Holt, Aaron; Hauser, Thomas | E71: Continuous Integration and Delivery for HPC: Using Singularity and Jenkins | F71: Proceedings of the Practice and Experience on Advanced Research Computing: Seamless Creativity | G71: 978-1-4503-6446-1 | I71: 10.1145/3219104.3219147 | J71: https://doi.org/10.1145/3219104.3219147 | K71: 2018 | L71: 45734.379 | M71: 45734.379 | V71: PEARC '18 | Z71: Association for Computing Machinery | AA71: New York, NY, USA | AI71: event-place: Pittsburgh, PA, USA | CL71: Continuous integration, delivery, and deployment (CICD) is widely used in DevOps communities, as it allows for teams of all sizes to deploy rapidly-changing hardware and software resources quickly and confidently. In this paper, we will describe how University of Colorado Boulder Research Computing has adopted these practices on the RMACC Summit supercomputer [17] to allow system engineers and researchers alike to capitalize on the benefits of CICD-centric development workflows. We will introduce the topic of CICD at a high level and describe how such practices can ease common software management challenges for High-Performance Computing (HPC) resources. We will then document the infrastructure deployed for Summit, and explain how software such as Jenkins and Singularity enabled adaptation for an HPC environment. We will conclude with two case studies discussing the use of our CICD infrastructure: one case study from the perspective of a system engineer maintaining user-facing resources, and the other case study from the perspective of a researcher developing, maintaining, and using the MFiX-Exa codebase. | DL71: containers; continuous delivery; continuous deployment; continuous integration; MFIX-Exa; Singularity; software automation; software builds
A72: 6RDIVRXX | B72: conferencePaper | C72: 2023 | D72: Li, Xiaojuan; Zhang, Yu; Zhu, Zhengyan; Yao, Yuan; Zhou, Xingshe | E72: UbiCap: A Capability-based Run-time Model for Heterogeneous Sensors Management in Ubiquitous Operating System | F72: Proceedings of the 14th Asia-Pacific Symposium on Internetware | G72: 979-8-4007-0894-7 | I72: 10.1145/3609437.3609448 | J72: https://doi.org/10.1145/3609437.3609448 | K72: 2023 | L72: 45734.379 | M72: 45734.379 | O72: 134‚Äì143 | V72: Internetware '23 | Z72: Association for Computing Machinery | AA72: New York, NY, USA | AI72: event-place: Hangzhou, China | CL72: The Ubiquitous Operating System(UOS) is a new type of operating system in response to the new patterns and scenarios of future human-cyber-physical ternary ubiquitous computing. Compared with traditional operating systems, one of the fundamental requirements of UOS is to adaptively manage numerous heterogeneous sensors according to dynamic environments and diverse tasks. However, traditional management focuses on the sensors‚Äô parameters and interfaces without highlighting the perception effect that is users‚Äô concern and dynamic changing. It also lacks a unified management approach for heterogeneous sensors. To overcome the limitations, we propose a novel heterogeneous sensors dynamic management model UbiCap, i.e., Ubiquitous Capability, which is based on the capability abstraction and adaptive run-time capability management mechanism. The capability provides a unified abstract for heterogeneous sensors. The adaptive run-time capability management mechanism transfers the management object from low-level hardware sensors to high-level sensing capability. The capability required and the available capability are matched to support run-time adaptive sensors selection. We implement a software prototype iS2ROS(intelligent Sensor Selection Robot Operating System) based on the UbiCap model. We then simulate a forest fire spot monitoring scenario where iS2ROS selects the optimal image sensor during the identification task execution while light or weather condition changes. Experiment results show that the iS2ROS achieves comparative sensing effectiveness through UbiCap with 50% power consumption lower compared to the traditional both-sensors approach. | DL72: adaptive; Capability; Heterogeneous Sensors Management; run-time; Ubiquitous Operating System
A73: 2FF54VYY | B73: conferencePaper | C73: 2020 | D73: Siavvas, Miltiadis; Tsoukalas, Dimitrios; Marantos, Charalampos; Tsintzira, Angeliki-Agathi; Jankovic, Marija; Soudris, Dimitrios; Chatzigeorgiou, Alexander; Kehagias, Dionysios | E73: The SDK4ED Platform for Embedded Software Quality Improvement - Preliminary Overview | F73: Computational Science and Its Applications ‚Äì ICCSA 2020: 20th International Conference, Cagliari, Italy, July 1‚Äì4, 2020, Proceedings, Part IV | G73: 978-3-030-58810-6 | I73: 10.1007/978-3-030-58811-3_73 | J73: https://doi.org/10.1007/978-3-030-58811-3_73 | K73: 2020 | L73: 45734.379 | M73: 45734.379 | O73: 1035‚Äì1050 | Z73: Springer-Verlag | AA73: Berlin, Heidelberg | AI73: event-place: Cagliari, Italy | CL73: Maintaining high level of quality with respect to important quality attributes is critical for the success of modern software applications. Hence, appropriate tooling is required to help developers and project managers monitor and optimize software quality throughout the overall Software Development Lifecycle (SDLC). Moreover, embedded software engineers and developers need support to manage complex interdependencies and inherent trade-offs between design and run-time qualities. To this end, in an attempt to address these issues, we are developing the SDK4ED Platform as part of the ongoing EU-funded SDK4ED project, a software quality system that enables the monitoring and optimization of software quality, with emphasis on embedded software. The purpose of this technical paper is to provide an overview of the SDK4ED Platform and present the main novel functionalities that have been implemented within the platform until today. | DL73: Software quality; Verification and validation
A74: DNEP97G4 | B74: conferencePaper | C74: 2024 | D74: Carlinet, Yannick; Perrot, Nancy; Valeyre, Laurent; Wary, Jean-Philippe; Bocianiak, Krzysztof; Niewolski, Wojciech; Podlasek, Aleksandra | E74: Latency-Sensitive Service Chaining with Isolation Constraints | F74: Proceedings of the 1st International Workshop on MetaOS for the Cloud-Edge-IoT Continuum | G74: 979-8-4007-0543-4 | I74: 10.1145/3642975.3678962 | J74: https://doi.org/10.1145/3642975.3678962 | K74: 2024 | L74: 45734.379 | M74: 45734.379 | O74: 8‚Äì13 | V74: MECC '24 | Z74: Association for Computing Machinery | AA74: New York, NY, USA | AI74: event-place: Athens, Greece | CL74: Multi-access Edge Computing (MEC) is one of the key enablers in 6G. By offering computing capabilities near the end users, it enables lower environmental impact, higher end-to-end latency, higher resiliency, among others. It is also a critical part in the Cloud-Edge-IoT continuum. However, the deployment of services in the edge poses some security challenges. This work aims at solving orchestration issues, such as how to deal with service deployment while meeting service-specific requirements, while at the same time meeting isolation requirements, in a multi-cluster environment. Our algorithm is estimated to be around 20% better than the baseline, while at the same time offering guarantees on the communication latency and isolation requirements, which the baseline cannot offer. We were able to build an orchestration engine, with an advanced algorithm to compute optimal placement of microservices, integrated in a state-of-art emulation platform, with industry best practice. This demonstrates the feasibility in practice and efficiency of our approach. | DL74: Edge Computing; Latency-sensitive Service; Multi-Edge Computing; Security Isolation; Service Chaining
A75: HERRS2B2 | B75: conferencePaper | C75: 2023 | D75: Yahya, Jawad Haj; Volos, Haris; Bartolini, Davide B.; Antoniou, Georgia; Kim, Jeremie S.; Wang, Zhe; Kalaitzidis, Kleovoulos; Rollet, Tom; Chen, Zhirui; Geng, Ye; Mutlu, Onur; Sazeides, Yiannakis | E75: AgileWatts: An Energy-Efficient CPU Core Idle-State Architecture for Latency-Sensitive Server Applications | F75: Proceedings of the 55th Annual IEEE/ACM International Symposium on Microarchitecture | G75: 978-1-6654-6272-3 | I75: 10.1109/MICRO56248.2022.00063 | J75: https://doi.org/10.1109/MICRO56248.2022.00063 | K75: 2023 | L75: 45734.379 | M75: 45734.379 | O75: 835‚Äì850 | V75: MICRO '22 | Z75: IEEE Press | AA75: Chicago, Illinois, USA | CL75: User-facing applications running in modern datacenters exhibit irregular request patterns and are implemented using a multitude of services with tight latency requirements (30‚Äì250Œºs). These characteristics render existing energy-conserving techniques ineffective when processors are idle due to the long transition time (order of 100Œºs) from a deep CPU core idle power state (C-state). While prior works propose management techniques to mitigate this inefficiency, we tackle it at its root with AgileWatts (AW): a new deep CPU core C-state architecture optimized for datacenter server processors targeting latency-sensitive applications.AW drastically reduces the transition latency from deep CPU core idle power states while retaining most of their power savings based on three key ideas. First, AW eliminates the latency (several microseconds) of saving/restoring the core context when powering-off/-on the core in a deep idle state by i) implementing medium-grained power-gates, carefully distributed across the CPU core, and ii) retaining context in the power-ungated domain. Second, AW eliminates the flush latency (several tens of microseconds) of the L1/L2 caches when entering a deep idle state by keeping L1/L2 content power-ungated. A small control logic also remains ungated to serve cache coherence traffic. AW implements cache sleep-mode and leakage reduction for the power-ungated domain by lowering a core's voltage to the minimum operational level. Third, using a state-of-the-art power efficient all-digital phase-locked loop (ADPLL) clock generator, AW keeps the PLL active and locked during the idle state, cutting microseconds of wake-up latency at negligible power cost.Our evaluation with an accurate industrial-grade simulator calibrated against an Intel Skylake server shows that AW reduces the energy consumption of Memcached by up to 71% (35% on average) with &lt;1% end-to-end performance degradation. We observe similar trends for other evaluated services (MySQL and Kafka). AW's new deep C-states C6A and C6AE reduce transition-time by up to 900√ó as compared to the deepest existing idle state C6, while consuming only 7% and 5% of the active state (C0) power, respectively.
A76: RHUMCMV2 | B76: conferencePaper | C76: 2023 | D76: Moussa, Mohamad; Glass, Philippe; Abdennahder, Nabil; Di Marzo Serugendo, Giovanna; Couturier, Rapha√´l | E76: Towards a&nbsp;Decentralised Federated Learning Based Compute Continuum Framework | F76: Service-Oriented and Cloud Computing: 10th IFIP WG 6.12 European Conference, ESOCC 2023, Larnaca, Cyprus, October 24‚Äì25, 2023, Proceedings | G76: 978-3-031-46234-4 | I76: 10.1007/978-3-031-46235-1_14 | J76: https://doi.org/10.1007/978-3-031-46235-1_14 | K76: 2023 | L76: 45734.379 | M76: 45734.379 | O76: 219‚Äì230 | Z76: Springer-Verlag | AA76: Berlin, Heidelberg | AI76: event-place: Larnaca, Cyprus | CL76: The proliferation of sensing device technologies, and the growing demand for data intensive IoT applications calls for a seamless interconnection of IoT, edge and cloud resources in one computing system, to form a Compute Continuum, also referred to as edge-to-cloud.This paper targets self-adaptive Machine Learning applications that rely on data coming from IoT sensors. These applications are often ‚Äúcontext-aware‚Äù, with high context sensitivity, different physical settings and complex usage patterns. Their intelligence, deployed on the edge, is updated on the fly.We present two Compute Continuum strategies for the deployment of such applications: (1) a centralised approach, which involves training a model on a centralised server, and (2) a decentralised approach using Federated Learning. The former approach involves centralising data from multiple sources onto a single server, while the latter locally decentralises both the training process and the aggregation and communication tasks across edge devices. In both cases the inference model is deployed on edge devices close to the collected data. The decentralised architecture relies on a coordination platform favouring self-adaptation and decentralised Federated Learning. Results show that the decentralised Federated Learning approach offers networking performances and privacy-preserving advantages compared to non-private centralised models, with a slight trade-off in prediction accuracy. According to our simulations, the deployment cost of the decentralised architecture is much lower than that of deployment on the centralised architecture. | DL76: Edge; Cloud; Compute Continuum; Coordination model; Federated Learning; Self-Adaptive IoT applications
A77: JWHIA5PE | B77: conferencePaper | C77: 2020 | D77: Bosak, T.; Jantos, P.; Boryczko, K. | E77: Simulation of a big number of microservices in a highly distributed vast network | F77: Proceedings of the 16th EAI International Conference on Mobile and Ubiquitous Systems: Computing, Networking and Services | G77: 978-1-4503-7283-1 | I77: 10.1145/3360774.3360790 | J77: https://doi.org/10.1145/3360774.3360790 | K77: 2020 | L77: 45734.379 | M77: 45734.379 | O77: 378‚Äì386 | V77: MobiQuitous '19 | Z77: Association for Computing Machinery | AA77: New York, NY, USA | AI77: event-place: Houston, Texas, USA | CL77: The rapidly increasing number of instances and types of services, especially microservices, and the growing complexity of systems create uncertainty if the existing algorithms and solutions for such problems as service discovery or load balancing are still the case. Building a huge infrastructure for the verification purposes is often too costly and impractical in the production environment therefore it is necessary to find other ways to test architectural approaches and algorithms. One of them is simulators. For simulating very big systems like a telecommunications radio access network the simulator should have certain features: capability of simulating a huge number of services, possibility to model heterogenic and vast network, facility to add a new type of services and logic. This paper presents a concept of such a simulator of services. | DL77: microservices; service discovery; simulation; edge cloud
A78: KJDXPW8G | B78: conferencePaper | C78: 2019 | D78: Hou, Xiaofeng; Liu, Jiacheng; Li, Chao; Guo, Minyi | E78: Unleashing the Scalability Potential of Power-Constrained Data Center in the Microservice Era | F78: Proceedings of the 48th International Conference on Parallel Processing | G78: 978-1-4503-6295-5 | I78: 10.1145/3337821.3337857 | J78: https://doi.org/10.1145/3337821.3337857 | K78: 2019 | L78: 45734.379 | M78: 45734.379 | V78: ICPP '19 | Z78: Association for Computing Machinery | AA78: New York, NY, USA | AI78: event-place: Kyoto, Japan | CL78: Recent scale-out cloud services have undergone a shift from monolithic applications to microservices by putting each functionality into lightweight software containers. Although traditional data center power optimization frameworks excel at per-server or per-rack management, they can hardly make informed decisions when facing microservices that have different QoS requirements on a per-service basis. In a power-constrained data center, blindly budgeting power usage could lead to a power unbalance issue: microservices on the critical path may not receive adequate power budget. This unavoidably hinders the growth of cloud productivity.To unleash the performance potential of cloud in the microservice era, this paper investigates microservice-aware data center resource management. We model microservice using a bipartite graph and propose a metric called microservice criticality factor (MCF) to measure the overall impact of performance scaling on a microservice from the whole application's perspective. We further devise ServiceFridge, a novel system framework that leverages MCF to jointly orchestrate software containers and control hardware power demand. Our detailed case study on a practical microservice application demonstrates that ServiceFridge allows data center to reduce its dynamic power by 25% with slight performance loss. It improves the mean response time by 25.2% and improves the 90th tail latency by 18.0% compared with existing schemes.
A79: ANESVB3I | B79: conferencePaper | C79: 2019 | D79: Carrusca, Andr√©; Gomes, Maria Cec√≠lia; Leit√£o, Jo√£o | E79: Microservices Management on Cloud/Edge Environments | F79: Service-Oriented Computing ‚Äì ICSOC 2019 Workshops: WESOACS, ASOCA, ISYCC, TBCE, and STRAPS, Toulouse, France, October 28‚Äì31, 2019, Revised Selected Papers | G79: 978-3-030-45988-8 | I79: 10.1007/978-3-030-45989-5_8 | J79: https://doi.org/10.1007/978-3-030-45989-5_8 | K79: 2019 | L79: 45734.379 | M79: 45734.379 | O79: 95‚Äì108 | Z79: Springer-Verlag | AA79: Berlin, Heidelberg | AI79: event-place: Toulouse, France | CL79: The microservices architecture is a promising approach for application development, deployment, and evolution, both on cloud and emerging fog/edge platforms. Microservices‚Äô single functionality, small size, and independent development/deployment support faster and cheaper scaling of pressing functionalities on cloud systems. They support applications‚Äô evolution via service reuse and smooth service modification/inclusion. Individual or sets of inter-related services may also be dynamically deployed onto resource-restricted nodes closer to end devices and data sources, which are typical of fog/edge computational platforms. The resulting system is very complex and impossible to be adequately managed manually. This work presents an automatic solution for microservices‚Äô deployment/replication in the fog/edge, adapting the system according to the runtime evaluation of client accesses and resource usage. The evaluation validates the adaptability and performance gains. | DL79: Cloud and fog/edge computing; Microservices architecture; Self-adaptable applications
A80: 7JQ4AXAP | B80: conferencePaper | C80: 2018 | D80: Muccini, Henry; Spalazzese, Romina; Moghaddam, Mahyar T.; Sharaf, Mohammad | E80: Self-adaptive IoT architectures: an emergency handling case study | F80: Proceedings of the 12th European Conference on Software Architecture: Companion Proceedings | G80: 978-1-4503-6483-6 | I80: 10.1145/3241403.3241424 | J80: https://doi.org/10.1145/3241403.3241424 | K80: 2018 | L80: 45734.379 | M80: 45734.379 | V80: ECSA '18 | Z80: Association for Computing Machinery | AA80: New York, NY, USA | AI80: event-place: Madrid, Spain | CL80: Along with the rapid growth of IoT technologies and devices, their solutions are currently being applied on various domains such as health-care, transportation and agriculture, but mainly on crowd monitoring and emergency handling. The latter is a safety critical IoT system based on collecting and analyzing the real-time data to perform proper actuation. In order to engineer such a high quality IoT application, a proper software architecture should be designed. In order for the software architecture to be able to optimize critical requirements such as fault-tolerance, performance and energy consumption, it ought to: i) adapt itself to real-time environment transformation, ii) be designed in a proper level of elements distribution. In this paper, we critically analyze a set of IoT distribution and self-adaptation patterns to identify their suitable architectural combinations. Further, we use our IoT modeling framework (CAPS) to model an emergency handling system. Based on these, we design two quality driven architectures to be used for a forest monitoring and evacuation example and qualitatively evaluate and compare them. | DL80: self-adaptation; IoT; architectural patterns and styles; quality attributes; urban security
A81: Y85IBBZD | B81: conferencePaper | C81: 2020 | D81: Dias, Jo√£o Pedro; Sousa, Tiago Boldt; Restivo, Andr√©; Ferreira, Hugo Sereno | E81: A Pattern-Language for Self-Healing Internet-of-Things Systems | F81: Proceedings of the European Conference on Pattern Languages of Programs 2020 | G81: 978-1-4503-7769-0 | I81: 10.1145/3424771.3424804 | J81: https://doi.org/10.1145/3424771.3424804 | K81: 2020 | L81: 45734.379 | M81: 45734.379 | V81: EuroPLoP '20 | Z81: Association for Computing Machinery | AA81: New York, NY, USA | AI81: event-place: Virtual Event, Germany | CL81: Internet-of-Things systems are assemblies of highly-distributed and heterogeneous parts that, in orchestration, work to provide valuable services to end-users in many scenarios. These systems depend on the correct operation of sensors, actuators, and third-party services, and the failure of a single one can hinder the proper functioning of the whole system, making error detection and recovery of paramount importance, but often overlooked. By drawing inspiration from other research areas, such as cloud, embedded, and mission-critical systems, we present a set of patterns for self-healing IoT systems. We discuss how their implementation can improve system reliability by providing error detection, error recovery, and health mechanisms maintenance. | DL81: fault-tolerance; internet-of-things; patterns; self-healing
A82: JL6V525G | B82: conferencePaper | C82: 2019 | D82: Neatu, Darius-Florentin; Stochitoiu, Radu-Dumitru; Postoaca, Andrei-Vlad; Filip, Ion-Dorinel; Pop, Florin | E82: My cloudy time machine: a scalable microservice-based platform for data processing in cloud-edge systems: a proof of concept for the ROBIN-cloud project | F82: Proceedings of the 34th ACM/SIGAPP Symposium on Applied Computing | G82: 978-1-4503-5933-7 | I82: 10.1145/3297280.3297427 | J82: https://doi.org/10.1145/3297280.3297427 | K82: 2019 | L82: 45734.379 | M82: 45734.379 | O82: 1451‚Äì1458 | V82: SAC '19 | Z82: Association for Computing Machinery | AA82: New York, NY, USA | AI82: event-place: Limassol, Cyprus | CL82: As Cloud computing is a very well developed domain, many companies tend to move their entire activity in Cloud. At the same time, there is a tendency to move some of the data processing from Cloud to Edge as close as possible to the end devices. One main advantage of this approach is minimizing the latency in communication between the end devices and Cloud. Better usage of on premise devices is also a good achievement of the Edge offload. In this paper, we propose an architecture for applications that are connected to ROBIN-Cloud or to a general Cloud. We present how we have encapsulated Python-based microservices in Docker containers. We provide an implementation for the My Cloudy Time Machine application - GIGEL (Guided Intelligent GEared Legend), a nearby autonomous assistive robot. We use this prototype to evaluate the scalability of the proposed architecture. We also present results that show how to gain high performance by tuning a container-based embedded system. | DL82: cloud computing; microservices; edge computing; auto-scalability; data processing
A83: NSM4L3PK | B83: conferencePaper | C83: 2021 | D83: Gilgur, Alexander; Coutinho, Brian; Narayanan, Iyswarya; Malani, Parth | E83: Transitive Power Modeling for Improving Resource Efficiency in a Hyperscale Datacenter | F83: Companion Proceedings of the Web Conference 2021 | G83: 978-1-4503-8313-4 | I83: 10.1145/3442442.3452057 | J83: https://doi.org/10.1145/3442442.3452057 | K83: 2021 | L83: 45734.379 | M83: 45734.379 | O83: 182‚Äì191 | V83: WWW '21 | Z83: Association for Computing Machinery | AA83: New York, NY, USA | AI83: event-place: Ljubljana, Slovenia | CL83: Maintaining efficient utilization of allocated compute resources and controlling their capital and operating expenditure is important for running a hyperscale datacenter infrastructure. Power is one of the most constrained and difficult to manage resources in datacenters. Accurate accounting of power usage across clients of multi-tenant web services can improve budgeting, planning and provisioning of compute resources. In this work, we propose a queuing theory based transitive power modeling framework that estimates the total power cost of a client request across the stack of shared services running in Facebook datacenters. By capturing the non-linearity of power vs load relation, our model is able to estimate marginal change in power consumption of a system upon serving a request with a mean error of less than 4% when applied on production services. In view of the fact that datacenter capacity is planned for peak demand, we test this model at peak load to report up to 2x improvement in accuracy compared to a mathematical model. We further leverage this framework along with a distributed tracing system to estimate power demand shift for serving particular product features within fraction of a percentage and guide the decision to shift their computation at off-peak time. | DL83: cpu; power; scalability; time shifting; transitive; utilization
A84: 2UFRLVDQ | B84: conferencePaper | C84: 2020 | D84: Gunasekaran, Jashwant Raj; Thinakaran, Prashanth; Nachiappan, Nachiappan C.; Kandemir, Mahmut Taylan; Das, Chita R. | E84: Fifer: Tackling Resource Underutilization in the Serverless Era | F84: Proceedings of the 21st International Middleware Conference | G84: 978-1-4503-8153-6 | I84: 10.1145/3423211.3425683 | J84: https://doi.org/10.1145/3423211.3425683 | K84: 2020 | L84: 45734.379 | M84: 45734.379 | O84: 280‚Äì295 | V84: Middleware '20 | Z84: Association for Computing Machinery | AA84: New York, NY, USA | AI84: event-place: Delft, Netherlands | CL84: Datacenters are witnessing a rapid surge in the adoption of serverless functions for microservices-based applications. A vast majority of these microservices typically span less than a second, have strict SLO requirements, and are chained together as per the requirements of an application. The aforementioned characteristics introduce a new set of challenges, especially in terms of container provisioning and management, as the state-of-the-art resource management frameworks, employed in serverless platforms, tend to look at microservice-based applications similar to conventional monolithic applications. Hence, these frameworks suffer from microservice agnostic scheduling and colossal container over-provisioning, especially during workload fluctuations, thereby resulting in poor resource utilization.In this work, we quantify the above shortcomings using a variety of workloads on a multi-node cluster managed by the Kubernetes and Brigade serverless framework. To address them, we propose Fifer ‚Äî an adaptive resource management framework to efficiently manage function-chains on serverless platforms. The key idea is to make Fifer (i) utilization conscious by efficiently bin packing jobs to fewer containers using function-aware container scaling and intelligent request batching, and (ii) at the same time, SLO-compliant by proactively spawning containers to avoid cold-starts, thus minimizing the overall response latency. Combining these benefits, Fifer improves container utilization and cluster-wide energy consumption by 4√ó and 31%, respectively, without compromising on SLO's, when compared to the state-of-the-art schedulers employed by serverless platforms. | DL84: scheduling; serverless; resource-management; queuing
A85: BV4DESPN | B85: conferencePaper | C85: 2024 | D85: Alho, Riku; Raatikainen, Mikko; Myllyaho, Lalli; Nurminen, Jukka K. | E85: On Modularity of&nbsp;Neural Networks: Systematic Review and&nbsp;Open Challenges | F85: Reuse and Software Quality: 21st International Conference on Software and Systems Reuse, ICSR 2024, Limassol, Cyprus, June 19‚Äì20, 2024, Proceedings | G85: 978-3-031-66458-8 | I85: 10.1007/978-3-031-66459-5_2 | J85: https://doi.org/10.1007/978-3-031-66459-5_2 | K85: 2024 | L85: 45734.379 | M85: 45734.379 | O85: 18‚Äì36 | Z85: Springer-Verlag | AA85: Berlin, Heidelberg | AI85: event-place: Limassol, Cyprus | CL85: Modularity is used to manage the complexity of monolithic software systems and is a de facto practice in software engineering. Similar modularity concepts might also translate beneficially to machine learning, uncovering equivalent benefits, such as reuse opportunities. We address the research problem of modular neural networks‚Äô (MNNs) applicability, operations, and comparability to monolithic solutions. A systematic literature review is used to identify 86 studies that provide information regarding modularity compared to monolithic solutions. The selected studies address many tasks and domains, evidencing broad applicability, although applied modularity operations are limited mainly to splitting. Nearly two-thirds of studies show improvements in task accuracy compared to monolithic solutions. Only 16% of studies report performance values in their comparisons, but 82% report MNN performance benefits in training and inference time, memory, and energy consumption compared to monolithic solutions. However, publication bias can favor MNNs, and most studies were conducted in laboratory environments on focused tasks and static requirements. Nevertheless, we conclude that MNNs perform at least satisfactorily compared to monolithic solutions. Modularity can bring forth benefits for managing complexity and has the potential for development and operations performance efficiency. Therefore, modularity in neural networks opens research avenues for extending software reuse, especially regarding broadening the applicability of advanced solutions and experiences from long-term or industrial applications and use. | DL85: deep learning; systematic literature review; modular neural networks; modularity
A86: 4YF3F6NQ | B86: conferencePaper | C86: 2019 | D86: Gaggero, Massimo; Busonera, Giovanni; Pireddu, Luca; Zanetti, Gianluigi | E86: TDM Edge Gateway: A Flexible Microservice-Based Edge Gateway Architecture for Heterogeneous Sensors | F86: Euro-Par 2019: Parallel Processing Workshops: Euro-Par 2019 International Workshops, G√∂ttingen, Germany, August 26‚Äì30, 2019, Revised Selected Papers | G86: 978-3-030-48339-5 | I86: 10.1007/978-3-030-48340-1_10 | J86: https://doi.org/10.1007/978-3-030-48340-1_10 | K86: 2019 | L86: 45734.379 | M86: 45734.379 | O86: 124‚Äì135 | Z86: Springer-Verlag | AA86: Berlin, Heidelberg | AI86: event-place: G√∂ttingen, Germany | CL86: How to effectively handle heterogeneous data sources is one of the main challenges in the design of large-scale research computing platforms to collect, analyze and integrate data from IoT sensors. The platform must seamlessly support the integration of myriads of data formats and communication protocols, many being introduced after the platform has been deployed. Edge gateways, devices deployed at the edge of the network near the sensors, communicate with measurement stations using their proper protocol, receive and translate the messages to a standardized format, forward the data to the processing platform and provide local data buffering and preprocessing. In this work we present the TDM Edge Gateway architecture, which we have developed to be used in research contexts to meet the requirements of being self-built, low-cost, and compatible with current or future connected sensors.The architecture is based on a microservice-oriented design implemented with software containerization and leverages publish/subscribe Inter Process Communication to ensure modularity and resiliency. Costs and construction simplicity are ensured by adopting the popular Raspberry Pi Single Board Computer. The resulting platform is lean, flexible and easy to expand and integrate. It does not pose constraints on programming languages to use and relies on standard protocols and data models. | DL86: Edge computing; Embedded; FIWARE; Sensor networks
A87: EDFBWZUP | B87: conferencePaper | C87: 2021 | D87: Ren, Haoyu; Anicic, Darko; Runkler, Thomas A. | E87: The synergy of complex event processing and tiny machine learning in industrial IoT | F87: Proceedings of the 15th ACM International Conference on Distributed and Event-Based Systems | G87: 978-1-4503-8555-8 | I87: 10.1145/3465480.3466928 | J87: https://doi.org/10.1145/3465480.3466928 | K87: 2021 | L87: 45734.379 | M87: 45734.379 | O87: 126‚Äì135 | V87: DEBS '21 | Z87: Association for Computing Machinery | AA87: New York, NY, USA | AI87: event-place: Virtual Event, Italy | CL87: Focusing on comprehensive networking, the Industrial Internet-of-Things (IIoT) facilitates efficiency and robustness in factory operations. Various intelligent sensors play a central role, as they generate a vast amount of real-time data that can provide insights into manufacturing. Complex event processing (CEP) and machine learning (ML) have been developed actively in the last years in IIoT to identify patterns in heterogeneous data streams and fuse raw data into tangible facts. In a traditional compute-centric paradigm, the raw field data are continuously sent to the cloud and processed centrally. As IIoT devices become increasingly pervasive, concerns are raised since transmitting such an amount of data is energy-intensive, vulnerable to be intercepted, and subjected to high latency. Decentralized on-device ML and CEP provide a solution where data is processed primarily on edge devices. Thus communications can be minimized. However, this is no mean feat because most IIoT edge devices are resource-constrained with low power consumption. This paper proposes a framework that exploits ML and CEP's synergy at the edge in distributed sensor networks. By leveraging tiny ML and ŒºCEP, we now shift the computation from the cloud to the resource-constrained IIoT devices and allow users to adapt on-device ML models and CEP reasoning rules flexibly on the fly. Lastly, we demonstrate the proposed solution and show its effectiveness and feasibility using an industrial use case of machine safety monitoring. | DL87: industrial IoT; complex event processing; tiny machine learning
A88: 6WYCE5T8 | B88: conferencePaper | C88: 2020 | D88: Matz, Alexandra; G√∂tz, Clarissa | E88: Designing Human-Centered Interactions for Smart Environments Based on Heterogeneous, Interrelated Systems: A User Research Method for the ‚ÄúAge of Services‚Äù (URSERVe) | F88: Design, User Experience, and Usability. Design for Contemporary Interactive Environments: 9th International Conference, DUXU 2020, Held as Part of the 22nd HCI International Conference, HCII 2020, Copenhagen, Denmark, July 19‚Äì24, 2020, Proceedings, Part II | G88: 978-3-030-49759-0 | I88: 10.1007/978-3-030-49760-6_7 | J88: https://doi.org/10.1007/978-3-030-49760-6_7 | K88: 2020 | L88: 45734.379 | M88: 45734.379 | O88: 99‚Äì116 | Z88: Springer-Verlag | AA88: Berlin, Heidelberg | AI88: event-place: Copenhagen, Denmark | CL88: Heterogeneous, interrelated systems leveraging the Internet of Things (IoT) in smart environments such as a smart factory or smart city, pose many challenges for software design and development. Capturing and addressing the human needs is one of them and designing the interactions within smart applications is another. There are several reasons for this, for example diverse personas for both human as well as digital actors, a large variety of usage scenarios, a vast number of data exchange protocols, as well as data privacy and ethical concerns.On top of this, the service-based architecture of smart environments has widened the gap between software development teams and their end users. Services are highly modular, decoupled units of application logic, developed for specific task units and as such they are one or even several hierarchy layers removed from the business logic of main applications, and, in consequence, from the applications‚Äô users. Therefore, in our experience, service development groups often refrain from identifying their users and doing any kind of user research at all. The reasoning being that, because their services will only be used by applications or other services, and not directly by human or non-human users, these users cannot be identified at all or are of no importance. This paper proposes a bidirectional, complementary method to approach user research for smart environments, such as smart cities. It describes how service development teams can reach beyond the applications which consume their service to the users of these consuming apps and how, at the same time, the smart city projects can reap the benefits of the technological expertise that resides in the service development groups. Ultimately, the method helps to create a shared knowledge base which arguably fosters innovation within an organization responsible for the design, development and operation of smart environments. | DL88: Microservices; Smart cities; Services; Human-centered design; Knowledge management; Smart environments; Smart factory; User centered design; User experience; User research
